Workbook

Sheet ReadMe - Validator Instructions
A1: Deal Flow Pipeline Tracker Toolkit - v1.0
A2: Post Fiat Analytical Infrastructure Library | LMM private equity deal sourcing | Formula-driven, anonymized
A4: Purpose
A5: Tracks bankers, brokers and other intermediaries, ranks a live deal pipeline with a transparent 0-100 priority score, and flags overdue deal next actions and lapsed intermediary touch cadences on one dashboard.
A7: How to use
A8: 1. Set the as-of date, EBITDA band, weights, stage probabilities and cadences on Settings and Scoring Rules (yellow cells).
A9: 2. Add intermediaries on Intermediary Directory A4:J28 and deals on Deal Pipeline Log A4:L43 (yellow cells; dropdowns validate stage, process, tier and ID).
A10: 3. Work the Follow-Up Cadence Tracker: every OVERDUE row is a call or email this week.
A11: 4. Read Ranking Dashboard B44 for the one-line pipeline output and B19:F23 for the top 5 deals.
A13: Tabs
A14: # | B14: Tab | C14: What it does
A15: 1 | B15: ReadMe - Validator Instructions | C15: Purpose, usage, validator checklist and formula reference
A16: 2 | B16: Settings and Scoring Rules | C16: Weights, stage probabilities, process scores, tier cadences, thresholds
A17: 3 | B17: Intermediary Directory | C17: Anonymized intermediary records plus live deal roll-ups
A18: 4 | B18: Deal Pipeline Log | C18: Deal log with stage, next action, priority score, rank and follow-up flag
A19: 5 | B19: Follow-Up Cadence Tracker | C19: Intermediary cadence and deal next-action follow-ups with overdue flags
A20: 6 | B20: Ranking Dashboard | C20: KPIs, top 5 ranked deals, stage funnel, most overdue, dashboard output
A21: 7 | B21: Anonymized Worked Example | C21: Sponsor X example: live snapshot, 4 named judgment calls, dashboard output
A23: Colour legend: yellow = input, blue = formula, green = key output. Tab 1 is 'ReadMe - Validator Instructions' because Excel does not allow '/' in tab names.
A25: Validator checklist (criterion -> tab -> cell range -> live check)
A26: # | B26: Criterion | C26: Tab | D26: Cell range | E26: Live check
A27: 1 | B27: Validator Read Me | C27: ReadMe - Validator Instructions | D27: A1:E45 | E27: ="Tabs in workbook: "&_xlfn.SHEETS() -> Tabs in workbook: 7
A28: 2 | B28: Anonymized intermediary directory | C28: Intermediary Directory | D28: A4:M28 | E28: =COUNTA('Intermediary Directory'!A4:A28)&" intermediaries, code names only" -> 10 intermediaries, code names only
A29: 3 | B29: Deal pipeline log with stage and next action | C29: Deal Pipeline Log | D29: A4:X43 (stage G, next action K/L) | E29: =COUNTA('Deal Pipeline Log'!$A$4:$A$43)&" deals; "&COUNTA('Deal Pipeline Log'!$K$4:$K$43)&" with a next action" -> 12 deals; 12 with a next action
A30: 4 | B30: Follow-up cadence tracker with overdue flags | C30: Follow-Up Cadence Tracker | D30: A5:K29 and A33:H72 | E30: ='Ranking Dashboard'!B12&" intermediary + "&'Ranking Dashboard'!B11&" deal follow-ups overdue" -> 4 intermediary + 4 deal follow-ups overdue
A31: 5 | B31: Live priority score and rank | C31: Deal Pipeline Log | D31: R4:T43; weights Settings B11:C16 | E31: ="Rank 1: "&'Ranking Dashboard'!B19&" ("&TEXT('Ranking Dashboard'!C19,"0.0")&")" -> Rank 1: Project Falcon (91.0)
A32: 6 | B32: Weights sum to 100% | C32: Settings and Scoring Rules | D32: B16:C16 | E32: ='Settings and Scoring Rules'!C16 -> OK - weights sum to 100%
A33: 7 | B33: Summary dashboard | C33: Ranking Dashboard | D33: A3:F45; output B44 | E33: ='Ranking Dashboard'!B15 -> AT RISK - 8 overdue follow-ups; clear backlog before new outreach
A34: 8 | B34: Anonymized worked example | C34: Anonymized Worked Example | D34: A1:G31 (4 judgment calls A20:G23) | E34: =COUNTA('Anonymized Worked Example'!A20:A23)&" judgment calls" -> 4 judgment calls
A35: 9 | B35: Visible live formulas | C35: ReadMe - Validator Instructions | D35: Formula reference A39:C43 (FORMULATEXT) | E35: =COUNTA(C39:C43)&" key formulas shown as live FORMULATEXT" -> 5 key formulas shown as live FORMULATEXT
A36: 10 | B36: Zero formula errors | C36: All tabs | D36: Excel SpecialCells(xlFormulas, xlErrors) scan | E36: See README.md (recalculated in Excel)
A38: Formula reference (live FORMULATEXT of key cells)
A39: 1 | B39: Priority score (Deal Pipeline Log R4) | C39: =_xlfn.FORMULATEXT('Deal Pipeline Log'!R4) -> =IF($A4="","",ROUND(100*('Settings and Scoring Rules'!$B$11*M4+'Settings and Scoring Rules'!$B$12*($I4-1)/4+'Settings and Scoring Rules'!$B$13*O4+'Settings and Scoring Rules'!$B$14*P4+'Settings and Scoring Rules'!$B$15*(Q4-1)/4),1))
A40: 2 | B40: Priority rank (Deal Pipeline Log T4) | C40: =_xlfn.FORMULATEXT('Deal Pipeline Log'!T4) -> =IF(S4="","",COUNTIF($S$4:$S$43,">"&S4)+1)
A41: 3 | B41: Follow-up flag (Deal Pipeline Log W4) | C41: =_xlfn.FORMULATEXT('Deal Pipeline Log'!W4) -> =IF($A4="","",IF(N4<>1,"Inactive - "&$G4,IF($L4="","NO NEXT ACTION",IF(V4>0,"OVERDUE "&V4&"d",IF($L4-'Settings and Scoring Rules'!$B$4<='Settings and Scoring Rules'!$B$7,"DUE IN "&($L4-'Settings and Scoring Rules'!$B$4)&"d",IF(N(U4)>'Settings and Scoring Rules'!$B$8,"STALE","On track"))))))
A42: 4 | B42: Cadence flag (Follow-Up Cadence Tracker I5) | C42: =_xlfn.FORMULATEXT('Follow-Up Cadence Tracker'!I5) -> =IF(A5="","",IF(H5>0,"OVERDUE "&H5&"d",IF(G5<='Settings and Scoring Rules'!$B$7,"DUE IN "&G5&"d","On track")))
A43: 5 | B43: Pipeline health (Ranking Dashboard B15) | C43: =_xlfn.FORMULATEXT('Ranking Dashboard'!B15) -> =IF(B11+B12=0,"HEALTHY - no overdue follow-ups",IF(B11+B12<=3,"ATTENTION - clear overdue follow-ups this week","AT RISK - "&(B11+B12)&" overdue follow-ups; clear backlog before new outreach"))

Sheet Settings and Scoring Rules
A1: Settings and Scoring Rules
A2: Yellow = input. Every weight, stage probability, cadence and threshold used by the model lives on this tab.
A3: Setting | B3: Value | C3: Unit | D3: Note
A4: As-of date | B4: 46299 | C4: date | D4: Fixed so the worked example is reproducible. For live use, replace with =TODAY().
A5: Target EBITDA band - minimum | B5: 3 | C5: $M | D5: Fund's lower-middle-market sweet spot.
A6: Target EBITDA band - maximum | B6: 15 | C6: $M | D6: Deals within 50% outside the band get half credit.
A7: Due-soon window | B7: 7 | C7: days | D7: Follow-ups due within this many days are flagged DUE IN Nd.
A8: Stale deal threshold | B8: 21 | C8: days | D8: Active deal with no near-term action and no activity for this long is flagged STALE.
A10: Priority score component | B10: Weight | D10: Definition (component scaled 0-1, score = 100 x weighted sum)
A11: Stage probability | B11: 0.3 | D11: Probability of close for the deal's stage (stage table below).
A12: Thesis fit | B12: 0.3 | D12: Analyst fit score 1-5, scaled (fit - 1) / 4.
A13: EBITDA size fit | B13: 0.15 | D13: 1.0 inside the band; 0.5 within 50% outside the band; 0 otherwise.
A14: Process quality | B14: 0.15 | D14: Process table below: proprietary deals score highest.
A15: Intermediary relationship | B15: 0.1 | D15: Relationship strength 1-5 from the directory, scaled (strength - 1) / 4.
A16: Total | B16: =SUM(B11:B15) -> 1 | C16: =IF(ROUND(B16,6)=1,"OK - weights sum to 100%","ERROR - weights must sum to 100%") -> OK - weights sum to 100%
A18: Stage | B18: Order | C18: Probability of close | D18: Active (1/0)
A19: Sourced | B19: 1 | C19: 0.05 | D19: 1
A20: NDA / Teaser | B20: 2 | C20: 0.1 | D20: 1
A21: CIM Review | B21: 3 | C21: 0.2 | D21: 1
A22: IOI Submitted | B22: 4 | C22: 0.35 | D22: 1
A23: Management Meeting | B23: 5 | C23: 0.5 | D23: 1
A24: LOI Submitted | B24: 6 | C24: 0.7 | D24: 1
A25: Exclusivity / Diligence | B25: 7 | C25: 0.85 | D25: 1
A26: Closed | B26: 8 | C26: 1 | D26: 0
A27: Passed | B27: 9 | C27: 0 | D27: 0
A28: Lost | B28: 10 | C28: 0 | D28: 0
A30: Process type | B30: Process score (0-1) | D30: Why
A31: Proprietary | B31: 1 | D31: No competing bidders; relationship-driven.
A32: Limited auction | B32: 0.6 | D32: Handful of invited buyers.
A33: Broad auction | B33: 0.2 | D33: Price-maximizing process; lowest win rate.
A35: Intermediary tier | B35: Touch cadence (days) | D35: Meaning
A36: A | B36: 14 | D36: Active deal source; every two weeks.
A37: B | B37: 30 | D37: Periodic source; monthly.
A38: C | B38: 60 | D38: Occasional source; every two months.

Sheet Intermediary Directory
A1: Intermediary Directory
A2: Anonymized bankers, brokers and other deal sources. Yellow = input (A-J); K-M are live roll-ups from the Deal Pipeline Log. Rows 4-28.
A3: ID | B3: Code name | C3: Type | D3: Firm code | E3: Region | F3: Sector focus | G3: Tier (A/B/C) | H3: Relationship strength (1-5) | I3: Last contact date | J3: Notes (anonymized) | K3: Deals sourced | L3: Active deals | M3: Best active priority score
A4: I01 | B4: Banker A | C4: Investment bank (LMM) | D4: Firm 1 | E4: Southeast | F4: Industrial services | G4: A | H4: 5 | I4: 46293 | J4: Runs limited auctions; sends early looks. | K4: =IF($A4="","",COUNTIF('Deal Pipeline Log'!$D$4:$D$43,$A4)) -> 1 | L4: =IF($A4="","",COUNTIFS('Deal Pipeline Log'!$D$4:$D$43,$A4,'Deal Pipeline Log'!$N$4:$N$43,1)) -> 1 | M4: =IF($A4="","",IF(L4=0,0,_xlfn.MAXIFS('Deal Pipeline Log'!$R$4:$R$43,'Deal Pipeline Log'!$D$4:$D$43,$A4,'Deal Pipeline Log'!$N$4:$N$43,1))) -> 79
A5: I02 | B5: Banker B | C5: Investment bank (LMM) | D5: Firm 2 | E5: Midwest | F5: Business services | G5: A | H5: 4 | I5: 46275 | J5: Broad auctions; strong deal volume. | K5: =IF($A5="","",COUNTIF('Deal Pipeline Log'!$D$4:$D$43,$A5)) -> 1 | L5: =IF($A5="","",COUNTIFS('Deal Pipeline Log'!$D$4:$D$43,$A5,'Deal Pipeline Log'!$N$4:$N$43,1)) -> 1 | M5: =IF($A5="","",IF(L5=0,0,_xlfn.MAXIFS('Deal Pipeline Log'!$R$4:$R$43,'Deal Pipeline Log'!$D$4:$D$43,$A5,'Deal Pipeline Log'!$N$4:$N$43,1))) -> 51
A6: I03 | B6: Broker C | C6: Business broker | D6: Firm 3 | E6: Texas | F6: Specialty distribution | G6: B | H6: 3 | I6: 46254 | J6: Owner-direct listings; light financials. | K6: =IF($A6="","",COUNTIF('Deal Pipeline Log'!$D$4:$D$43,$A6)) -> 2 | L6: =IF($A6="","",COUNTIFS('Deal Pipeline Log'!$D$4:$D$43,$A6,'Deal Pipeline Log'!$N$4:$N$43,1)) -> 2 | M6: =IF($A6="","",IF(L6=0,0,_xlfn.MAXIFS('Deal Pipeline Log'!$R$4:$R$43,'Deal Pipeline Log'!$D$4:$D$43,$A6,'Deal Pipeline Log'!$N$4:$N$43,1))) -> 63.5
A7: I04 | B7: Broker D | C7: Business broker | D7: Firm 4 | E7: Southeast | F7: Home services | G7: B | H7: 4 | I7: 46287 | J7: Regional roll-up candidates. | K7: =IF($A7="","",COUNTIF('Deal Pipeline Log'!$D$4:$D$43,$A7)) -> 2 | L7: =IF($A7="","",COUNTIFS('Deal Pipeline Log'!$D$4:$D$43,$A7,'Deal Pipeline Log'!$N$4:$N$43,1)) -> 1 | M7: =IF($A7="","",IF(L7=0,0,_xlfn.MAXIFS('Deal Pipeline Log'!$R$4:$R$43,'Deal Pipeline Log'!$D$4:$D$43,$A7,'Deal Pipeline Log'!$N$4:$N$43,1))) -> 57
A8: I05 | B8: Advisor E | C8: M&A advisory boutique | D8: Firm 5 | E8: Northeast | F8: Healthcare services | G8: A | H8: 3 | I8: 46288 | J8: Larger deals; often above our band. | K8: =IF($A8="","",COUNTIF('Deal Pipeline Log'!$D$4:$D$43,$A8)) -> 1 | L8: =IF($A8="","",COUNTIFS('Deal Pipeline Log'!$D$4:$D$43,$A8,'Deal Pipeline Log'!$N$4:$N$43,1)) -> 1 | M8: =IF($A8="","",IF(L8=0,0,_xlfn.MAXIFS('Deal Pipeline Log'!$R$4:$R$43,'Deal Pipeline Log'!$D$4:$D$43,$A8,'Deal Pipeline Log'!$N$4:$N$43,1))) -> 36.5
A9: I06 | B9: CPA F | C9: Accounting firm | D9: Firm 6 | E9: Midwest | F9: Owner-operator businesses | G9: C | H9: 4 | I9: 46218 | J9: Succession-planning clients. | K9: =IF($A9="","",COUNTIF('Deal Pipeline Log'!$D$4:$D$43,$A9)) -> 1 | L9: =IF($A9="","",COUNTIFS('Deal Pipeline Log'!$D$4:$D$43,$A9,'Deal Pipeline Log'!$N$4:$N$43,1)) -> 1 | M9: =IF($A9="","",IF(L9=0,0,_xlfn.MAXIFS('Deal Pipeline Log'!$R$4:$R$43,'Deal Pipeline Log'!$D$4:$D$43,$A9,'Deal Pipeline Log'!$N$4:$N$43,1))) -> 54
A10: I07 | B10: Attorney G | C10: Law firm (M&A) | D10: Firm 7 | E10: Texas | F10: Industrial services | G10: C | H10: 3 | I10: 46266 | J10: Estate and succession referrals. | K10: =IF($A10="","",COUNTIF('Deal Pipeline Log'!$D$4:$D$43,$A10)) -> 1 | L10: =IF($A10="","",COUNTIFS('Deal Pipeline Log'!$D$4:$D$43,$A10,'Deal Pipeline Log'!$N$4:$N$43,1)) -> 1 | M10: =IF($A10="","",IF(L10=0,0,_xlfn.MAXIFS('Deal Pipeline Log'!$R$4:$R$43,'Deal Pipeline Log'!$D$4:$D$43,$A10,'Deal Pipeline Log'!$N$4:$N$43,1))) -> 62
A11: I08 | B11: Operator H | C11: Former executive | D11: n/a | E11: Southeast | F11: Industrial services | G11: B | H11: 5 | I11: 46295 | J11: Operating partner candidate; proprietary intros. | K11: =IF($A11="","",COUNTIF('Deal Pipeline Log'!$D$4:$D$43,$A11)) -> 1 | L11: =IF($A11="","",COUNTIFS('Deal Pipeline Log'!$D$4:$D$43,$A11,'Deal Pipeline Log'!$N$4:$N$43,1)) -> 1 | M11: =IF($A11="","",IF(L11=0,0,_xlfn.MAXIFS('Deal Pipeline Log'!$R$4:$R$43,'Deal Pipeline Log'!$D$4:$D$43,$A11,'Deal Pipeline Log'!$N$4:$N$43,1))) -> 91
A12: I09 | B12: Banker I | C12: Investment bank (LMM) | D12: Firm 8 | E12: West | F12: Software-enabled services | G12: B | H12: 2 | I12: 46203 | J12: Relationship cooled after a passed deal. | K12: =IF($A12="","",COUNTIF('Deal Pipeline Log'!$D$4:$D$43,$A12)) -> 1 | L12: =IF($A12="","",COUNTIFS('Deal Pipeline Log'!$D$4:$D$43,$A12,'Deal Pipeline Log'!$N$4:$N$43,1)) -> 0 | M12: =IF($A12="","",IF(L12=0,0,_xlfn.MAXIFS('Deal Pipeline Log'!$R$4:$R$43,'Deal Pipeline Log'!$D$4:$D$43,$A12,'Deal Pipeline Log'!$N$4:$N$43,1))) -> 0
A13: I10 | B13: Founder J | C13: Founder network | D13: n/a | E13: Midwest | F13: Business services | G13: C | H13: 4 | I13: 46280 | J13: Peer founders considering exits. | K13: =IF($A13="","",COUNTIF('Deal Pipeline Log'!$D$4:$D$43,$A13)) -> 1 | L13: =IF($A13="","",COUNTIFS('Deal Pipeline Log'!$D$4:$D$43,$A13,'Deal Pipeline Log'!$N$4:$N$43,1)) -> 1 | M13: =IF($A13="","",IF(L13=0,0,_xlfn.MAXIFS('Deal Pipeline Log'!$R$4:$R$43,'Deal Pipeline Log'!$D$4:$D$43,$A13,'Deal Pipeline Log'!$N$4:$N$43,1))) -> 61.5
K14: =IF($A14="","",COUNTIF('Deal Pipeline Log'!$D$4:$D$43,$A14)) | L14: =IF($A14="","",COUNTIFS('Deal Pipeline Log'!$D$4:$D$43,$A14,'Deal Pipeline Log'!$N$4:$N$43,1)) | M14: =IF($A14="","",IF(L14=0,0,_xlfn.MAXIFS('Deal Pipeline Log'!$R$4:$R$43,'Deal Pipeline Log'!$D$4:$D$43,$A14,'Deal Pipeline Log'!$N$4:$N$43,1)))
K15: =IF($A15="","",COUNTIF('Deal Pipeline Log'!$D$4:$D$43,$A15)) | L15: =IF($A15="","",COUNTIFS('Deal Pipeline Log'!$D$4:$D$43,$A15,'Deal Pipeline Log'!$N$4:$N$43,1)) | M15: =IF($A15="","",IF(L15=0,0,_xlfn.MAXIFS('Deal Pipeline Log'!$R$4:$R$43,'Deal Pipeline Log'!$D$4:$D$43,$A15,'Deal Pipeline Log'!$N$4:$N$43,1)))
K16: =IF($A16="","",COUNTIF('Deal Pipeline Log'!$D$4:$D$43,$A16)) | L16: =IF($A16="","",COUNTIFS('Deal Pipeline Log'!$D$4:$D$43,$A16,'Deal Pipeline Log'!$N$4:$N$43,1)) | M16: =IF($A16="","",IF(L16=0,0,_xlfn.MAXIFS('Deal Pipeline Log'!$R$4:$R$43,'Deal Pipeline Log'!$D$4:$D$43,$A16,'Deal Pipeline Log'!$N$4:$N$43,1)))
K17: =IF($A17="","",COUNTIF('Deal Pipeline Log'!$D$4:$D$43,$A17)) | L17: =IF($A17="","",COUNTIFS('Deal Pipeline Log'!$D$4:$D$43,$A17,'Deal Pipeline Log'!$N$4:$N$43,1)) | M17: =IF($A17="","",IF(L17=0,0,_xlfn.MAXIFS('Deal Pipeline Log'!$R$4:$R$43,'Deal Pipeline Log'!$D$4:$D$43,$A17,'Deal Pipeline Log'!$N$4:$N$43,1)))
K18: =IF($A18="","",COUNTIF('Deal Pipeline Log'!$D$4:$D$43,$A18)) | L18: =IF($A18="","",COUNTIFS('Deal Pipeline Log'!$D$4:$D$43,$A18,'Deal Pipeline Log'!$N$4:$N$43,1)) | M18: =IF($A18="","",IF(L18=0,0,_xlfn.MAXIFS('Deal Pipeline Log'!$R$4:$R$43,'Deal Pipeline Log'!$D$4:$D$43,$A18,'Deal Pipeline Log'!$N$4:$N$43,1)))
K19: =IF($A19="","",COUNTIF('Deal Pipeline Log'!$D$4:$D$43,$A19)) | L19: =IF($A19="","",COUNTIFS('Deal Pipeline Log'!$D$4:$D$43,$A19,'Deal Pipeline Log'!$N$4:$N$43,1)) | M19: =IF($A19="","",IF(L19=0,0,_xlfn.MAXIFS('Deal Pipeline Log'!$R$4:$R$43,'Deal Pipeline Log'!$D$4:$D$43,$A19,'Deal Pipeline Log'!$N$4:$N$43,1)))
K20: =IF($A20="","",COUNTIF('Deal Pipeline Log'!$D$4:$D$43,$A20)) | L20: =IF($A20="","",COUNTIFS('Deal Pipeline Log'!$D$4:$D$43,$A20,'Deal Pipeline Log'!$N$4:$N$43,1)) | M20: =IF($A20="","",IF(L20=0,0,_xlfn.MAXIFS('Deal Pipeline Log'!$R$4:$R$43,'Deal Pipeline Log'!$D$4:$D$43,$A20,'Deal Pipeline Log'!$N$4:$N$43,1)))
K21: =IF($A21="","",COUNTIF('Deal Pipeline Log'!$D$4:$D$43,$A21)) | L21: =IF($A21="","",COUNTIFS('Deal Pipeline Log'!$D$4:$D$43,$A21,'Deal Pipeline Log'!$N$4:$N$43,1)) | M21: =IF($A21="","",IF(L21=0,0,_xlfn.MAXIFS('Deal Pipeline Log'!$R$4:$R$43,'Deal Pipeline Log'!$D$4:$D$43,$A21,'Deal Pipeline Log'!$N$4:$N$43,1)))
K22: =IF($A22="","",COUNTIF('Deal Pipeline Log'!$D$4:$D$43,$A22)) | L22: =IF($A22="","",COUNTIFS('Deal Pipeline Log'!$D$4:$D$43,$A22,'Deal Pipeline Log'!$N$4:$N$43,1)) | M22: =IF($A22="","",IF(L22=0,0,_xlfn.MAXIFS('Deal Pipeline Log'!$R$4:$R$43,'Deal Pipeline Log'!$D$4:$D$43,$A22,'Deal Pipeline Log'!$N$4:$N$43,1)))
K23: =IF($A23="","",COUNTIF('Deal Pipeline Log'!$D$4:$D$43,$A23)) | L23: =IF($A23="","",COUNTIFS('Deal Pipeline Log'!$D$4:$D$43,$A23,'Deal Pipeline Log'!$N$4:$N$43,1)) | M23: =IF($A23="","",IF(L23=0,0,_xlfn.MAXIFS('Deal Pipeline Log'!$R$4:$R$43,'Deal Pipeline Log'!$D$4:$D$43,$A23,'Deal Pipeline Log'!$N$4:$N$43,1)))
K24: =IF($A24="","",COUNTIF('Deal Pipeline Log'!$D$4:$D$43,$A24)) | L24: =IF($A24="","",COUNTIFS('Deal Pipeline Log'!$D$4:$D$43,$A24,'Deal Pipeline Log'!$N$4:$N$43,1)) | M24: =IF($A24="","",IF(L24=0,0,_xlfn.MAXIFS('Deal Pipeline Log'!$R$4:$R$43,'Deal Pipeline Log'!$D$4:$D$43,$A24,'Deal Pipeline Log'!$N$4:$N$43,1)))
K25: =IF($A25="","",COUNTIF('Deal Pipeline Log'!$D$4:$D$43,$A25)) | L25: =IF($A25="","",COUNTIFS('Deal Pipeline Log'!$D$4:$D$43,$A25,'Deal Pipeline Log'!$N$4:$N$43,1)) | M25: =IF($A25="","",IF(L25=0,0,_xlfn.MAXIFS('Deal Pipeline Log'!$R$4:$R$43,'Deal Pipeline Log'!$D$4:$D$43,$A25,'Deal Pipeline Log'!$N$4:$N$43,1)))
... K28: =IF($A28="","",COUNTIF('Deal Pipeline Log'!$D$4:$D$43,$A28)) | L28: =IF($A28="","",COUNTIFS('Deal Pipeline Log'!$D$4:$D$43,$A28,'Deal Pipeline Log'!$N$4:$N$43,1)) | M28: =IF($A28="","",IF(L28=0,0,_xlfn.MAXIFS('Deal Pipeline Log'!$R$4:$R$43,'Deal Pipeline Log'!$D$4:$D$43,$A28,'Deal Pipeline Log'!$N$4:$N$43,1)))

Sheet Deal Pipeline Log
A1: Deal Pipeline Log
A2: One row per opportunity. Yellow = input (A-L); blue = live formulas (M-X). Priority score, rank and follow-up flag recalculate from Settings. Rows 4-43.
A3: Deal ID | B3: Code name | C3: Sector | D3: Intermediary ID | E3: Intermediary (lookup) | F3: Process type | G3: Stage | H3: LTM EBITDA ($M) | I3: Thesis fit (1-5) | J3: Last activity date | K3: Next action | L3: Next action due | M3: Stage probability | N3: Active (1/0) | O3: EBITDA size fit | P3: Process score | Q3: Relationship strength | R3: Priority score (0-100) | S3: Rank key (tie-break) | T3: Priority rank (active) | U3: Days since last activity | V3: Days overdue | W3: Follow-up flag | X3: Prob.-weighted EBITDA ($M)
A4: D01 | B4: Project Atlas | C4: Industrial services | D4: I01 | E4: =IF($D4="","",IFERROR(INDEX('Intermediary Directory'!$B$4:$B$28,MATCH($D4,'Intermediary Directory'!$A$4:$A$28,0)),"UNKNOWN ID")) -> Banker A | F4: Limited auction | G4: Management Meeting | H4: 6.5 | I4: 5 | J4: 46295 | K4: Send diligence request list | L4: 46303 | M4: =IF($A4="","",IFERROR(VLOOKUP($G4,'Settings and Scoring Rules'!$A$19:$D$28,3,FALSE),0)) -> 0.5 | N4: =IF($A4="","",IFERROR(VLOOKUP($G4,'Settings and Scoring Rules'!$A$19:$D$28,4,FALSE),0)) -> 1 | O4: =IF($A4="","",IF(AND($H4>='Settings and Scoring Rules'!$B$5,$H4<='Settings and Scoring Rules'!$B$6),1,IF(AND($H4>='Settings and Scoring Rules'!$B$5*0.5,$H4<='Settings and Scoring Rules'!$B$6*1.5),0.5,0))) -> 1 | P4: =IF($A4="","",IFERROR(VLOOKUP($F4,'Settings and Scoring Rules'!$A$31:$B$33,2,FALSE),0)) -> 0.6 | Q4: =IF($A4="","",IFERROR(INDEX('Intermediary Directory'!$H$4:$H$28,MATCH($D4,'Intermediary Directory'!$A$4:$A$28,0)),1)) -> 5 | R4: =IF($A4="","",ROUND(100*('Settings and Scoring Rules'!$B$11*M4+'Settings and Scoring Rules'!$B$12*($I4-1)/4+'Settings and Scoring Rules'!$B$13*O4+'Settings and Scoring Rules'!$B$14*P4+'Settings and Scoring Rules'!$B$15*(Q4-1)/4),1)) -> 79 | S4: =IF(OR($A4="",N4<>1),"",R4+(1000-ROW())/10^7) -> 79.0001 | T4: =IF(S4="","",COUNTIF($S$4:$S$43,">"&S4)+1) -> 2 | U4: =IF(OR($A4="",$J4=""),"",'Settings and Scoring Rules'!$B$4-$J4) -> 4 | V4: =IF(OR($A4="",N4<>1,$L4=""),"",MAX(0,'Settings and Scoring Rules'!$B$4-$L4)) -> 0 | W4: =IF($A4="","",IF(N4<>1,"Inactive - "&$G4,IF($L4="","NO NEXT ACTION",IF(V4>0,"OVERDUE "&V4&"d",IF($L4-'Settings and Scoring Rules'!$B$4<='Settings and Scoring Rules'!$B$7,"DUE IN "&($L4-'Settings and Scoring Rules'!$B$4)&"d",IF(N(U4)>'Settings and Scoring Rules'!$B$8,"STALE","On track")))))) -> DUE IN 4d | X4: =IF($A4="","",$H4*M4*N4) -> 3.25
A5: D02 | B5: Project Birch | C5: Business services | D5: I02 | E5: =IF($D5="","",IFERROR(INDEX('Intermediary Directory'!$B$4:$B$28,MATCH($D5,'Intermediary Directory'!$A$4:$A$28,0)),"UNKNOWN ID")) -> Banker B | F5: Broad auction | G5: IOI Submitted | H5: 9 | I5: 3 | J5: 46283 | K5: Follow up on IOI feedback | L5: 46294 | M5: =IF($A5="","",IFERROR(VLOOKUP($G5,'Settings and Scoring Rules'!$A$19:$D$28,3,FALSE),0)) -> 0.35 | N5: =IF($A5="","",IFERROR(VLOOKUP($G5,'Settings and Scoring Rules'!$A$19:$D$28,4,FALSE),0)) -> 1 | O5: =IF($A5="","",IF(AND($H5>='Settings and Scoring Rules'!$B$5,$H5<='Settings and Scoring Rules'!$B$6),1,IF(AND($H5>='Settings and Scoring Rules'!$B$5*0.5,$H5<='Settings and Scoring Rules'!$B$6*1.5),0.5,0))) -> 1 | P5: =IF($A5="","",IFERROR(VLOOKUP($F5,'Settings and Scoring Rules'!$A$31:$B$33,2,FALSE),0)) -> 0.2 | Q5: =IF($A5="","",IFERROR(INDEX('Intermediary Directory'!$H$4:$H$28,MATCH($D5,'Intermediary Directory'!$A$4:$A$28,0)),1)) -> 4 | R5: =IF($A5="","",ROUND(100*('Settings and Scoring Rules'!$B$11*M5+'Settings and Scoring Rules'!$B$12*($I5-1)/4+'Settings and Scoring Rules'!$B$13*O5+'Settings and Scoring Rules'!$B$14*P5+'Settings and Scoring Rules'!$B$15*(Q5-1)/4),1)) -> 51 | S5: =IF(OR($A5="",N5<>1),"",R5+(1000-ROW())/10^7) -> 51.000099 | T5: =IF(S5="","",COUNTIF($S$4:$S$43,">"&S5)+1) -> 8 | U5: =IF(OR($A5="",$J5=""),"",'Settings and Scoring Rules'!$B$4-$J5) -> 16 | V5: =IF(OR($A5="",N5<>1,$L5=""),"",MAX(0,'Settings and Scoring Rules'!$B$4-$L5)) -> 5 | W5: =IF($A5="","",IF(N5<>1,"Inactive - "&$G5,IF($L5="","NO NEXT ACTION",IF(V5>0,"OVERDUE "&V5&"d",IF($L5-'Settings and Scoring Rules'!$B$4<='Settings and Scoring Rules'!$B$7,"DUE IN "&($L5-'Settings and Scoring Rules'!$B$4)&"d",IF(N(U5)>'Settings and Scoring Rules'!$B$8,"STALE","On track")))))) -> OVERDUE 5d | X5: =IF($A5="","",$H5*M5*N5) -> 3.15
A6: D03 | B6: Project Cedar | C6: Specialty distribution | D6: I03 | E6: =IF($D6="","",IFERROR(INDEX('Intermediary Directory'!$B$4:$B$28,MATCH($D6,'Intermediary Directory'!$A$4:$A$28,0)),"UNKNOWN ID")) -> Broker C | F6: Proprietary | G6: CIM Review | H6: 4.2 | I6: 4 | J6: 46277 | K6: Call owner re: Q3 financials | L6: 46291 | M6: =IF($A6="","",IFERROR(VLOOKUP($G6,'Settings and Scoring Rules'!$A$19:$D$28,3,FALSE),0)) -> 0.2 | N6: =IF($A6="","",IFERROR(VLOOKUP($G6,'Settings and Scoring Rules'!$A$19:$D$28,4,FALSE),0)) -> 1 | O6: =IF($A6="","",IF(AND($H6>='Settings and Scoring Rules'!$B$5,$H6<='Settings and Scoring Rules'!$B$6),1,IF(AND($H6>='Settings and Scoring Rules'!$B$5*0.5,$H6<='Settings and Scoring Rules'!$B$6*1.5),0.5,0))) -> 1 | P6: =IF($A6="","",IFERROR(VLOOKUP($F6,'Settings and Scoring Rules'!$A$31:$B$33,2,FALSE),0)) -> 1 | Q6: =IF($A6="","",IFERROR(INDEX('Intermediary Directory'!$H$4:$H$28,MATCH($D6,'Intermediary Directory'!$A$4:$A$28,0)),1)) -> 3 | R6: =IF($A6="","",ROUND(100*('Settings and Scoring Rules'!$B$11*M6+'Settings and Scoring Rules'!$B$12*($I6-1)/4+'Settings and Scoring Rules'!$B$13*O6+'Settings and Scoring Rules'!$B$14*P6+'Settings and Scoring Rules'!$B$15*(Q6-1)/4),1)) -> 63.5 | S6: =IF(OR($A6="",N6<>1),"",R6+(1000-ROW())/10^7) -> 63.500099 | T6: =IF(S6="","",COUNTIF($S$4:$S$43,">"&S6)+1) -> 3 | U6: =IF(OR($A6="",$J6=""),"",'Settings and Scoring Rules'!$B$4-$J6) -> 22 | V6: =IF(OR($A6="",N6<>1,$L6=""),"",MAX(0,'Settings and Scoring Rules'!$B$4-$L6)) -> 8 | W6: =IF($A6="","",IF(N6<>1,"Inactive - "&$G6,IF($L6="","NO NEXT ACTION",IF(V6>0,"OVERDUE "&V6&"d",IF($L6-'Settings and Scoring Rules'!$B$4<='Settings and Scoring Rules'!$B$7,"DUE IN "&($L6-'Settings and Scoring Rules'!$B$4)&"d",IF(N(U6)>'Settings and Scoring Rules'!$B$8,"STALE","On track")))))) -> OVERDUE 8d | X6: =IF($A6="","",$H6*M6*N6) -> 0.84
A7: D04 | B7: Project Delta | C7: Home services | D7: I04 | E7: =IF($D7="","",IFERROR(INDEX('Intermediary Directory'!$B$4:$B$28,MATCH($D7,'Intermediary Directory'!$A$4:$A$28,0)),"UNKNOWN ID")) -> Broker D | F7: Limited auction | G7: NDA / Teaser | H7: 3.1 | I7: 4 | J7: 46290 | K7: Sign NDA and request CIM | L7: 46298 | M7: =IF($A7="","",IFERROR(VLOOKUP($G7,'Settings and Scoring Rules'!$A$19:$D$28,3,FALSE),0)) -> 0.1 | N7: =IF($A7="","",IFERROR(VLOOKUP($G7,'Settings and Scoring Rules'!$A$19:$D$28,4,FALSE),0)) -> 1 | O7: =IF($A7="","",IF(AND($H7>='Settings and Scoring Rules'!$B$5,$H7<='Settings and Scoring Rules'!$B$6),1,IF(AND($H7>='Settings and Scoring Rules'!$B$5*0.5,$H7<='Settings and Scoring Rules'!$B$6*1.5),0.5,0))) -> 1 | P7: =IF($A7="","",IFERROR(VLOOKUP($F7,'Settings and Scoring Rules'!$A$31:$B$33,2,FALSE),0)) -> 0.6 | Q7: =IF($A7="","",IFERROR(INDEX('Intermediary Directory'!$H$4:$H$28,MATCH($D7,'Intermediary Directory'!$A$4:$A$28,0)),1)) -> 4 | R7: =IF($A7="","",ROUND(100*('Settings and Scoring Rules'!$B$11*M7+'Settings and Scoring Rules'!$B$12*($I7-1)/4+'Settings and Scoring Rules'!$B$13*O7+'Settings and Scoring Rules'!$B$14*P7+'Settings and Scoring Rules'!$B$15*(Q7-1)/4),1)) -> 57 | S7: =IF(OR($A7="",N7<>1),"",R7+(1000-ROW())/10^7) -> 57.000099 | T7: =IF(S7="","",COUNTIF($S$4:$S$43,">"&S7)+1) -> 6 | U7: =IF(OR($A7="",$J7=""),"",'Settings and Scoring Rules'!$B$4-$J7) -> 9 | V7: =IF(OR($A7="",N7<>1,$L7=""),"",MAX(0,'Settings and Scoring Rules'!$B$4-$L7)) -> 1 | W7: =IF($A7="","",IF(N7<>1,"Inactive - "&$G7,IF($L7="","NO NEXT ACTION",IF(V7>0,"OVERDUE "&V7&"d",IF($L7-'Settings and Scoring Rules'!$B$4<='Settings and Scoring Rules'!$B$7,"DUE IN "&($L7-'Settings and Scoring Rules'!$B$4)&"d",IF(N(U7)>'Settings and Scoring Rules'!$B$8,"STALE","On track")))))) -> OVERDUE 1d | X7: =IF($A7="","",$H7*M7*N7) -> 0.31
A8: D05 | B8: Project Ember | C8: Healthcare services | D8: I05 | E8: =IF($D8="","",IFERROR(INDEX('Intermediary Directory'!$B$4:$B$28,MATCH($D8,'Intermediary Directory'!$A$4:$A$28,0)),"UNKNOWN ID")) -> Advisor E | F8: Broad auction | G8: CIM Review | H8: 18 | I8: 3 | J8: 46289 | K8: Decide IOI go / no-go | L8: 46305 | M8: =IF($A8="","",IFERROR(VLOOKUP($G8,'Settings and Scoring Rules'!$A$19:$D$28,3,FALSE),0)) -> 0.2 | N8: =IF($A8="","",IFERROR(VLOOKUP($G8,'Settings and Scoring Rules'!$A$19:$D$28,4,FALSE),0)) -> 1 | O8: =IF($A8="","",IF(AND($H8>='Settings and Scoring Rules'!$B$5,$H8<='Settings and Scoring Rules'!$B$6),1,IF(AND($H8>='Settings and Scoring Rules'!$B$5*0.5,$H8<='Settings and Scoring Rules'!$B$6*1.5),0.5,0))) -> 0.5 | P8: =IF($A8="","",IFERROR(VLOOKUP($F8,'Settings and Scoring Rules'!$A$31:$B$33,2,FALSE),0)) -> 0.2 | Q8: =IF($A8="","",IFERROR(INDEX('Intermediary Directory'!$H$4:$H$28,MATCH($D8,'Intermediary Directory'!$A$4:$A$28,0)),1)) -> 3 | R8: =IF($A8="","",ROUND(100*('Settings and Scoring Rules'!$B$11*M8+'Settings and Scoring Rules'!$B$12*($I8-1)/4+'Settings and Scoring Rules'!$B$13*O8+'Settings and Scoring Rules'!$B$14*P8+'Settings and Scoring Rules'!$B$15*(Q8-1)/4),1)) -> 36.5 | S8: =IF(OR($A8="",N8<>1),"",R8+(1000-ROW())/10^7) -> 36.500099 | T8: =IF(S8="","",COUNTIF($S$4:$S$43,">"&S8)+1) -> 10 | U8: =IF(OR($A8="",$J8=""),"",'Settings and Scoring Rules'!$B$4-$J8) -> 10 | V8: =IF(OR($A8="",N8<>1,$L8=""),"",MAX(0,'Settings and Scoring Rules'!$B$4-$L8)) -> 0 | W8: =IF($A8="","",IF(N8<>1,"Inactive - "&$G8,IF($L8="","NO NEXT ACTION",IF(V8>0,"OVERDUE "&V8&"d",IF($L8-'Settings and Scoring Rules'!$B$4<='Settings and Scoring Rules'!$B$7,"DUE IN "&($L8-'Settings and Scoring Rules'!$B$4)&"d",IF(N(U8)>'Settings and Scoring Rules'!$B$8,"STALE","On track")))))) -> DUE IN 6d | X8: =IF($A8="","",$H8*M8*N8) -> 3.6
A9: D06 | B9: Project Falcon | C9: Industrial services | D9: I08 | E9: =IF($D9="","",IFERROR(INDEX('Intermediary Directory'!$B$4:$B$28,MATCH($D9,'Intermediary Directory'!$A$4:$A$28,0)),"UNKNOWN ID")) -> Operator H | F9: Proprietary | G9: LOI Submitted | H9: 7.8 | I9: 5 | J9: 46296 | K9: Negotiate LOI exclusivity terms | L9: 46301 | M9: =IF($A9="","",IFERROR(VLOOKUP($G9,'Settings and Scoring Rules'!$A$19:$D$28,3,FALSE),0)) -> 0.7 | N9: =IF($A9="","",IFERROR(VLOOKUP($G9,'Settings and Scoring Rules'!$A$19:$D$28,4,FALSE),0)) -> 1 | O9: =IF($A9="","",IF(AND($H9>='Settings and Scoring Rules'!$B$5,$H9<='Settings and Scoring Rules'!$B$6),1,IF(AND($H9>='Settings and Scoring Rules'!$B$5*0.5,$H9<='Settings and Scoring Rules'!$B$6*1.5),0.5,0))) -> 1 | P9: =IF($A9="","",IFERROR(VLOOKUP($F9,'Settings and Scoring Rules'!$A$31:$B$33,2,FALSE),0)) -> 1 | Q9: =IF($A9="","",IFERROR(INDEX('Intermediary Directory'!$H$4:$H$28,MATCH($D9,'Intermediary Directory'!$A$4:$A$28,0)),1)) -> 5 | R9: =IF($A9="","",ROUND(100*('Settings and Scoring Rules'!$B$11*M9+'Settings and Scoring Rules'!$B$12*($I9-1)/4+'Settings and Scoring Rules'!$B$13*O9+'Settings and Scoring Rules'!$B$14*P9+'Settings and Scoring Rules'!$B$15*(Q9-1)/4),1)) -> 91 | S9: =IF(OR($A9="",N9<>1),"",R9+(1000-ROW())/10^7) -> 91.000099 | T9: =IF(S9="","",COUNTIF($S$4:$S$43,">"&S9)+1) -> 1 | U9: =IF(OR($A9="",$J9=""),"",'Settings and Scoring Rules'!$B$4-$J9) -> 3 | V9: =IF(OR($A9="",N9<>1,$L9=""),"",MAX(0,'Settings and Scoring Rules'!$B$4-$L9)) -> 0 | W9: =IF($A9="","",IF(N9<>1,"Inactive - "&$G9,IF($L9="","NO NEXT ACTION",IF(V9>0,"OVERDUE "&V9&"d",IF($L9-'Settings and Scoring Rules'!$B$4<='Settings and Scoring Rules'!$B$7,"DUE IN "&($L9-'Settings and Scoring Rules'!$B$4)&"d",IF(N(U9)>'Settings and Scoring Rules'!$B$8,"STALE","On track")))))) -> DUE IN 2d | X9: =IF($A9="","",$H9*M9*N9) -> 5.46
A10: D07 | B10: Project Granite | C10: Owner-operator businesses | D10: I06 | E10: =IF($D10="","",IFERROR(INDEX('Intermediary Directory'!$B$4:$B$28,MATCH($D10,'Intermediary Directory'!$A$4:$A$28,0)),"UNKNOWN ID")) -> CPA F | F10: Proprietary | G10: Sourced | H10: 2.4 | I10: 4 | J10: 46264 | K10: Schedule intro call with owner | L10: 46280 | M10: =IF($A10="","",IFERROR(VLOOKUP($G10,'Settings and Scoring Rules'!$A$19:$D$28,3,FALSE),0)) -> 0.05 | N10: =IF($A10="","",IFERROR(VLOOKUP($G10,'Settings and Scoring Rules'!$A$19:$D$28,4,FALSE),0)) -> 1 | O10: =IF($A10="","",IF(AND($H10>='Settings and Scoring Rules'!$B$5,$H10<='Settings and Scoring Rules'!$B$6),1,IF(AND($H10>='Settings and Scoring Rules'!$B$5*0.5,$H10<='Settings and Scoring Rules'!$B$6*1.5),0.5,0))) -> 0.5 | P10: =IF($A10="","",IFERROR(VLOOKUP($F10,'Settings and Scoring Rules'!$A$31:$B$33,2,FALSE),0)) -> 1 | Q10: =IF($A10="","",IFERROR(INDEX('Intermediary Directory'!$H$4:$H$28,MATCH($D10,'Intermediary Directory'!$A$4:$A$28,0)),1)) -> 4 | R10: =IF($A10="","",ROUND(100*('Settings and Scoring Rules'!$B$11*M10+'Settings and Scoring Rules'!$B$12*($I10-1)/4+'Settings and Scoring Rules'!$B$13*O10+'Settings and Scoring Rules'!$B$14*P10+'Settings and Scoring Rules'!$B$15*(Q10-1)/4),1)) -> 54 | S10: =IF(OR($A10="",N10<>1),"",R10+(1000-ROW())/10^7) -> 54.000099 | T10: =IF(S10="","",COUNTIF($S$4:$S$43,">"&S10)+1) -> 7 | U10: =IF(OR($A10="",$J10=""),"",'Settings and Scoring Rules'!$B$4-$J10) -> 35 | V10: =IF(OR($A10="",N10<>1,$L10=""),"",MAX(0,'Settings and Scoring Rules'!$B$4-$L10)) -> 19 | W10: =IF($A10="","",IF(N10<>1,"Inactive - "&$G10,IF($L10="","NO NEXT ACTION",IF(V10>0,"OVERDUE "&V10&"d",IF($L10-'Settings and Scoring Rules'!$B$4<='Settings and Scoring Rules'!$B$7,"DUE IN "&($L10-'Settings and Scoring Rules'!$B$4)&"d",IF(N(U10)>'Settings and Scoring Rules'!$B$8,"STALE","On track")))))) -> OVERDUE 19d | X10: =IF($A10="","",$H10*M10*N10) -> 0.12
A11: D08 | B11: Project Harbor | C11: Software-enabled services | D11: I09 | E11: =IF($D11="","",IFERROR(INDEX('Intermediary Directory'!$B$4:$B$28,MATCH($D11,'Intermediary Directory'!$A$4:$A$28,0)),"UNKNOWN ID")) -> Banker I | F11: Broad auction | G11: Passed | H11: 11 | I11: 2 | J11: 46249 | K11: Passed - valuation gap | M11: =IF($A11="","",IFERROR(VLOOKUP($G11,'Settings and Scoring Rules'!$A$19:$D$28,3,FALSE),0)) -> 0 | N11: =IF($A11="","",IFERROR(VLOOKUP($G11,'Settings and Scoring Rules'!$A$19:$D$28,4,FALSE),0)) -> 0 | O11: =IF($A11="","",IF(AND($H11>='Settings and Scoring Rules'!$B$5,$H11<='Settings and Scoring Rules'!$B$6),1,IF(AND($H11>='Settings and Scoring Rules'!$B$5*0.5,$H11<='Settings and Scoring Rules'!$B$6*1.5),0.5,0))) -> 1 | P11: =IF($A11="","",IFERROR(VLOOKUP($F11,'Settings and Scoring Rules'!$A$31:$B$33,2,FALSE),0)) -> 0.2 | Q11: =IF($A11="","",IFERROR(INDEX('Intermediary Directory'!$H$4:$H$28,MATCH($D11,'Intermediary Directory'!$A$4:$A$28,0)),1)) -> 2 | R11: =IF($A11="","",ROUND(100*('Settings and Scoring Rules'!$B$11*M11+'Settings and Scoring Rules'!$B$12*($I11-1)/4+'Settings and Scoring Rules'!$B$13*O11+'Settings and Scoring Rules'!$B$14*P11+'Settings and Scoring Rules'!$B$15*(Q11-1)/4),1)) -> 28 | S11: =IF(OR($A11="",N11<>1),"",R11+(1000-ROW())/10^7) | T11: =IF(S11="","",COUNTIF($S$4:$S$43,">"&S11)+1) | U11: =IF(OR($A11="",$J11=""),"",'Settings and Scoring Rules'!$B$4-$J11) -> 50 | V11: =IF(OR($A11="",N11<>1,$L11=""),"",MAX(0,'Settings and Scoring Rules'!$B$4-$L11)) | W11: =IF($A11="","",IF(N11<>1,"Inactive - "&$G11,IF($L11="","NO NEXT ACTION",IF(V11>0,"OVERDUE "&V11&"d",IF($L11-'Settings and Scoring Rules'!$B$4<='Settings and Scoring Rules'!$B$7,"DUE IN "&($L11-'Settings and Scoring Rules'!$B$4)&"d",IF(N(U11)>'Settings and Scoring Rules'!$B$8,"STALE","On track")))))) -> Inactive - Passed | X11: =IF($A11="","",$H11*M11*N11) -> 0
A12: D09 | B12: Project Iris | C12: Business services | D12: I10 | E12: =IF($D12="","",IFERROR(INDEX('Intermediary Directory'!$B$4:$B$28,MATCH($D12,'Intermediary Directory'!$A$4:$A$28,0)),"UNKNOWN ID")) -> Founder J | F12: Proprietary | G12: Sourced | H12: 5.5 | I12: 4 | J12: 46285 | K12: Request financial summary | L12: 46307 | M12: =IF($A12="","",IFERROR(VLOOKUP($G12,'Settings and Scoring Rules'!$A$19:$D$28,3,FALSE),0)) -> 0.05 | N12: =IF($A12="","",IFERROR(VLOOKUP($G12,'Settings and Scoring Rules'!$A$19:$D$28,4,FALSE),0)) -> 1 | O12: =IF($A12="","",IF(AND($H12>='Settings and Scoring Rules'!$B$5,$H12<='Settings and Scoring Rules'!$B$6),1,IF(AND($H12>='Settings and Scoring Rules'!$B$5*0.5,$H12<='Settings and Scoring Rules'!$B$6*1.5),0.5,0))) -> 1 | P12: =IF($A12="","",IFERROR(VLOOKUP($F12,'Settings and Scoring Rules'!$A$31:$B$33,2,FALSE),0)) -> 1 | Q12: =IF($A12="","",IFERROR(INDEX('Intermediary Directory'!$H$4:$H$28,MATCH($D12,'Intermediary Directory'!$A$4:$A$28,0)),1)) -> 4 | R12: =IF($A12="","",ROUND(100*('Settings and Scoring Rules'!$B$11*M12+'Settings and Scoring Rules'!$B$12*($I12-1)/4+'Settings and Scoring Rules'!$B$13*O12+'Settings and Scoring Rules'!$B$14*P12+'Settings and Scoring Rules'!$B$15*(Q12-1)/4),1)) -> 61.5 | S12: =IF(OR($A12="",N12<>1),"",R12+(1000-ROW())/10^7) -> 61.500099 | T12: =IF(S12="","",COUNTIF($S$4:$S$43,">"&S12)+1) -> 5 | U12: =IF(OR($A12="",$J12=""),"",'Settings and Scoring Rules'!$B$4-$J12) -> 14 | V12: =IF(OR($A12="",N12<>1,$L12=""),"",MAX(0,'Settings and Scoring Rules'!$B$4-$L12)) -> 0 | W12: =IF($A12="","",IF(N12<>1,"Inactive - "&$G12,IF($L12="","NO NEXT ACTION",IF(V12>0,"OVERDUE "&V12&"d",IF($L12-'Settings and Scoring Rules'!$B$4<='Settings and Scoring Rules'!$B$7,"DUE IN "&($L12-'Settings and Scoring Rules'!$B$4)&"d",IF(N(U12)>'Settings and Scoring Rules'!$B$8,"STALE","On track")))))) -> On track | X12: =IF($A12="","",$H12*M12*N12) -> 0.275
A13: D10 | B13: Project Juniper | C13: Industrial services | D13: I07 | E13: =IF($D13="","",IFERROR(INDEX('Intermediary Directory'!$B$4:$B$28,MATCH($D13,'Intermediary Directory'!$A$4:$A$28,0)),"UNKNOWN ID")) -> Attorney G | F13: Limited auction | G13: IOI Submitted | H13: 12.5 | I13: 4 | J13: 46291 | K13: Prepare management meeting questions | L13: 46304 | M13: =IF($A13="","",IFERROR(VLOOKUP($G13,'Settings and Scoring Rules'!$A$19:$D$28,3,FALSE),0)) -> 0.35 | N13: =IF($A13="","",IFERROR(VLOOKUP($G13,'Settings and Scoring Rules'!$A$19:$D$28,4,FALSE),0)) -> 1 | O13: =IF($A13="","",IF(AND($H13>='Settings and Scoring Rules'!$B$5,$H13<='Settings and Scoring Rules'!$B$6),1,IF(AND($H13>='Settings and Scoring Rules'!$B$5*0.5,$H13<='Settings and Scoring Rules'!$B$6*1.5),0.5,0))) -> 1 | P13: =IF($A13="","",IFERROR(VLOOKUP($F13,'Settings and Scoring Rules'!$A$31:$B$33,2,FALSE),0)) -> 0.6 | Q13: =IF($A13="","",IFERROR(INDEX('Intermediary Directory'!$H$4:$H$28,MATCH($D13,'Intermediary Directory'!$A$4:$A$28,0)),1)) -> 3 | R13: =IF($A13="","",ROUND(100*('Settings and Scoring Rules'!$B$11*M13+'Settings and Scoring Rules'!$B$12*($I13-1)/4+'Settings and Scoring Rules'!$B$13*O13+'Settings and Scoring Rules'!$B$14*P13+'Settings and Scoring Rules'!$B$15*(Q13-1)/4),1)) -> 62 | S13: =IF(OR($A13="",N13<>1),"",R13+(1000-ROW())/10^7) -> 62.000099 | T13: =IF(S13="","",COUNTIF($S$4:$S$43,">"&S13)+1) -> 4 | U13: =IF(OR($A13="",$J13=""),"",'Settings and Scoring Rules'!$B$4-$J13) -> 8 | V13: =IF(OR($A13="",N13<>1,$L13=""),"",MAX(0,'Settings and Scoring Rules'!$B$4-$L13)) -> 0 | W13: =IF($A13="","",IF(N13<>1,"Inactive - "&$G13,IF($L13="","NO NEXT ACTION",IF(V13>0,"OVERDUE "&V13&"d",IF($L13-'Settings and Scoring Rules'!$B$4<='Settings and Scoring Rules'!$B$7,"DUE IN "&($L13-'Settings and Scoring Rules'!$B$4)&"d",IF(N(U13)>'Settings and Scoring Rules'!$B$8,"STALE","On track")))))) -> DUE IN 5d | X13: =IF($A13="","",$H13*M13*N13) -> 4.375
A14: D11 | B14: Project Kestrel | C14: Home services | D14: I04 | E14: =IF($D14="","",IFERROR(INDEX('Intermediary Directory'!$B$4:$B$28,MATCH($D14,'Intermediary Directory'!$A$4:$A$28,0)),"UNKNOWN ID")) -> Broker D | F14: Broad auction | G14: Lost | H14: 8 | I14: 3 | J14: 46270 | K14: Lost - outbid | M14: =IF($A14="","",IFERROR(VLOOKUP($G14,'Settings and Scoring Rules'!$A$19:$D$28,3,FALSE),0)) -> 0 | N14: =IF($A14="","",IFERROR(VLOOKUP($G14,'Settings and Scoring Rules'!$A$19:$D$28,4,FALSE),0)) -> 0 | O14: =IF($A14="","",IF(AND($H14>='Settings and Scoring Rules'!$B$5,$H14<='Settings and Scoring Rules'!$B$6),1,IF(AND($H14>='Settings and Scoring Rules'!$B$5*0.5,$H14<='Settings and Scoring Rules'!$B$6*1.5),0.5,0))) -> 1 | P14: =IF($A14="","",IFERROR(VLOOKUP($F14,'Settings and Scoring Rules'!$A$31:$B$33,2,FALSE),0)) -> 0.2 | Q14: =IF($A14="","",IFERROR(INDEX('Intermediary Directory'!$H$4:$H$28,MATCH($D14,'Intermediary Directory'!$A$4:$A$28,0)),1)) -> 4 | R14: =IF($A14="","",ROUND(100*('Settings and Scoring Rules'!$B$11*M14+'Settings and Scoring Rules'!$B$12*($I14-1)/4+'Settings and Scoring Rules'!$B$13*O14+'Settings and Scoring Rules'!$B$14*P14+'Settings and Scoring Rules'!$B$15*(Q14-1)/4),1)) -> 40.5 | S14: =IF(OR($A14="",N14<>1),"",R14+(1000-ROW())/10^7) | T14: =IF(S14="","",COUNTIF($S$4:$S$43,">"&S14)+1) | U14: =IF(OR($A14="",$J14=""),"",'Settings and Scoring Rules'!$B$4-$J14) -> 29 | V14: =IF(OR($A14="",N14<>1,$L14=""),"",MAX(0,'Settings and Scoring Rules'!$B$4-$L14)) | W14: =IF($A14="","",IF(N14<>1,"Inactive - "&$G14,IF($L14="","NO NEXT ACTION",IF(V14>0,"OVERDUE "&V14&"d",IF($L14-'Settings and Scoring Rules'!$B$4<='Settings and Scoring Rules'!$B$7,"DUE IN "&($L14-'Settings and Scoring Rules'!$B$4)&"d",IF(N(U14)>'Settings and Scoring Rules'!$B$8,"STALE","On track")))))) -> Inactive - Lost | X14: =IF($A14="","",$H14*M14*N14) -> 0
A15: D12 | B15: Project Larch | C15: Specialty distribution | D15: I03 | E15: =IF($D15="","",IFERROR(INDEX('Intermediary Directory'!$B$4:$B$28,MATCH($D15,'Intermediary Directory'!$A$4:$A$28,0)),"UNKNOWN ID")) -> Broker C | F15: Limited auction | G15: NDA / Teaser | H15: 6 | I15: 3 | J15: 46294 | K15: Review teaser vs thesis | L15: 46309 | M15: =IF($A15="","",IFERROR(VLOOKUP($G15,'Settings and Scoring Rules'!$A$19:$D$28,3,FALSE),0)) -> 0.1 | N15: =IF($A15="","",IFERROR(VLOOKUP($G15,'Settings and Scoring Rules'!$A$19:$D$28,4,FALSE),0)) -> 1 | O15: =IF($A15="","",IF(AND($H15>='Settings and Scoring Rules'!$B$5,$H15<='Settings and Scoring Rules'!$B$6),1,IF(AND($H15>='Settings and Scoring Rules'!$B$5*0.5,$H15<='Settings and Scoring Rules'!$B$6*1.5),0.5,0))) -> 1 | P15: =IF($A15="","",IFERROR(VLOOKUP($F15,'Settings and Scoring Rules'!$A$31:$B$33,2,FALSE),0)) -> 0.6 | Q15: =IF($A15="","",IFERROR(INDEX('Intermediary Directory'!$H$4:$H$28,MATCH($D15,'Intermediary Directory'!$A$4:$A$28,0)),1)) -> 3 | R15: =IF($A15="","",ROUND(100*('Settings and Scoring Rules'!$B$11*M15+'Settings and Scoring Rules'!$B$12*($I15-1)/4+'Settings and Scoring Rules'!$B$13*O15+'Settings and Scoring Rules'!$B$14*P15+'Settings and Scoring Rules'!$B$15*(Q15-1)/4),1)) -> 47 | S15: =IF(OR($A15="",N15<>1),"",R15+(1000-ROW())/10^7) -> 47.000099 | T15: =IF(S15="","",COUNTIF($S$4:$S$43,">"&S15)+1) -> 9 | U15: =IF(OR($A15="",$J15=""),"",'Settings and Scoring Rules'!$B$4-$J15) -> 5 | V15: =IF(OR($A15="",N15<>1,$L15=""),"",MAX(0,'Settings and Scoring Rules'!$B$4-$L15)) -> 0 | W15: =IF($A15="","",IF(N15<>1,"Inactive - "&$G15,IF($L15="","NO NEXT ACTION",IF(V15>0,"OVERDUE "&V15&"d",IF($L15-'Settings and Scoring Rules'!$B$4<='Settings and Scoring Rules'!$B$7,"DUE IN "&($L15-'Settings and Scoring Rules'!$B$4)&"d",IF(N(U15)>'Settings and Scoring Rules'!$B$8,"STALE","On track")))))) -> On track | X15: =IF($A15="","",$H15*M15*N15) -> 0.6
E16: =IF($D16="","",IFERROR(INDEX('Intermediary Directory'!$B$4:$B$28,MATCH($D16,'Intermediary Directory'!$A$4:$A$28,0)),"UNKNOWN ID")) | M16: =IF($A16="","",IFERROR(VLOOKUP($G16,'Settings and Scoring Rules'!$A$19:$D$28,3,FALSE),0)) | N16: =IF($A16="","",IFERROR(VLOOKUP($G16,'Settings and Scoring Rules'!$A$19:$D$28,4,FALSE),0)) | O16: =IF($A16="","",IF(AND($H16>='Settings and Scoring Rules'!$B$5,$H16<='Settings and Scoring Rules'!$B$6),1,IF(AND($H16>='Settings and Scoring Rules'!$B$5*0.5,$H16<='Settings and Scoring Rules'!$B$6*1.5),0.5,0))) | P16: =IF($A16="","",IFERROR(VLOOKUP($F16,'Settings and Scoring Rules'!$A$31:$B$33,2,FALSE),0)) | Q16: =IF($A16="","",IFERROR(INDEX('Intermediary Directory'!$H$4:$H$28,MATCH($D16,'Intermediary Directory'!$A$4:$A$28,0)),1)) | R16: =IF($A16="","",ROUND(100*('Settings and Scoring Rules'!$B$11*M16+'Settings and Scoring Rules'!$B$12*($I16-1)/4+'Settings and Scoring Rules'!$B$13*O16+'Settings and Scoring Rules'!$B$14*P16+'Settings and Scoring Rules'!$B$15*(Q16-1)/4),1)) | S16: =IF(OR($A16="",N16<>1),"",R16+(1000-ROW())/10^7) | T16: =IF(S16="","",COUNTIF($S$4:$S$43,">"&S16)+1) | U16: =IF(OR($A16="",$J16=""),"",'Settings and Scoring Rules'!$B$4-$J16) | V16: =IF(OR($A16="",N16<>1,$L16=""),"",MAX(0,'Settings and Scoring Rules'!$B$4-$L16)) | W16: =IF($A16="","",IF(N16<>1,"Inactive - "&$G16,IF($L16="","NO NEXT ACTION",IF(V16>0,"OVERDUE "&V16&"d",IF($L16-'Settings and Scoring Rules'!$B$4<='Settings and Scoring Rules'!$B$7,"DUE IN "&($L16-'Settings and Scoring Rules'!$B$4)&"d",IF(N(U16)>'Settings and Scoring Rules'!$B$8,"STALE","On track")))))) | X16: =IF($A16="","",$H16*M16*N16)
E17: =IF($D17="","",IFERROR(INDEX('Intermediary Directory'!$B$4:$B$28,MATCH($D17,'Intermediary Directory'!$A$4:$A$28,0)),"UNKNOWN ID")) | M17: =IF($A17="","",IFERROR(VLOOKUP($G17,'Settings and Scoring Rules'!$A$19:$D$28,3,FALSE),0)) | N17: =IF($A17="","",IFERROR(VLOOKUP($G17,'Settings and Scoring Rules'!$A$19:$D$28,4,FALSE),0)) | O17: =IF($A17="","",IF(AND($H17>='Settings and Scoring Rules'!$B$5,$H17<='Settings and Scoring Rules'!$B$6),1,IF(AND($H17>='Settings and Scoring Rules'!$B$5*0.5,$H17<='Settings and Scoring Rules'!$B$6*1.5),0.5,0))) | P17: =IF($A17="","",IFERROR(VLOOKUP($F17,'Settings and Scoring Rules'!$A$31:$B$33,2,FALSE),0)) | Q17: =IF($A17="","",IFERROR(INDEX('Intermediary Directory'!$H$4:$H$28,MATCH($D17,'Intermediary Directory'!$A$4:$A$28,0)),1)) | R17: =IF($A17="","",ROUND(100*('Settings and Scoring Rules'!$B$11*M17+'Settings and Scoring Rules'!$B$12*($I17-1)/4+'Settings and Scoring Rules'!$B$13*O17+'Settings and Scoring Rules'!$B$14*P17+'Settings and Scoring Rules'!$B$15*(Q17-1)/4),1)) | S17: =IF(OR($A17="",N17<>1),"",R17+(1000-ROW())/10^7) | T17: =IF(S17="","",COUNTIF($S$4:$S$43,">"&S17)+1) | U17: =IF(OR($A17="",$J17=""),"",'Settings and Scoring Rules'!$B$4-$J17) | V17: =IF(OR($A17="",N17<>1,$L17=""),"",MAX(0,'Settings and Scoring Rules'!$B$4-$L17)) | W17: =IF($A17="","",IF(N17<>1,"Inactive - "&$G17,IF($L17="","NO NEXT ACTION",IF(V17>0,"OVERDUE "&V17&"d",IF($L17-'Settings and Scoring Rules'!$B$4<='Settings and Scoring Rules'!$B$7,"DUE IN "&($L17-'Settings and Scoring Rules'!$B$4)&"d",IF(N(U17)>'Settings and Scoring Rules'!$B$8,"STALE","On track")))))) | X17: =IF($A17="","",$H17*M17*N17)
E18: =IF($D18="","",IFERROR(INDEX('Intermediary Directory'!$B$4:$B$28,MATCH($D18,'Intermediary Directory'!$A$4:$A$28,0)),"UNKNOWN ID")) | M18: =IF($A18="","",IFERROR(VLOOKUP($G18,'Settings and Scoring Rules'!$A$19:$D$28,3,FALSE),0)) | N18: =IF($A18="","",IFERROR(VLOOKUP($G18,'Settings and Scoring Rules'!$A$19:$D$28,4,FALSE),0)) | O18: =IF($A18="","",IF(AND($H18>='Settings and Scoring Rules'!$B$5,$H18<='Settings and Scoring Rules'!$B$6),1,IF(AND($H18>='Settings and Scoring Rules'!$B$5*0.5,$H18<='Settings and Scoring Rules'!$B$6*1.5),0.5,0))) | P18: =IF($A18="","",IFERROR(VLOOKUP($F18,'Settings and Scoring Rules'!$A$31:$B$33,2,FALSE),0)) | Q18: =IF($A18="","",IFERROR(INDEX('Intermediary Directory'!$H$4:$H$28,MATCH($D18,'Intermediary Directory'!$A$4:$A$28,0)),1)) | R18: =IF($A18="","",ROUND(100*('Settings and Scoring Rules'!$B$11*M18+'Settings and Scoring Rules'!$B$12*($I18-1)/4+'Settings and Scoring Rules'!$B$13*O18+'Settings and Scoring Rules'!$B$14*P18+'Settings and Scoring Rules'!$B$15*(Q18-1)/4),1)) | S18: =IF(OR($A18="",N18<>1),"",R18+(1000-ROW())/10^7) | T18: =IF(S18="","",COUNTIF($S$4:$S$43,">"&S18)+1) | U18: =IF(OR($A18="",$J18=""),"",'Settings and Scoring Rules'!$B$4-$J18) | V18: =IF(OR($A18="",N18<>1,$L18=""),"",MAX(0,'Settings and Scoring Rules'!$B$4-$L18)) | W18: =IF($A18="","",IF(N18<>1,"Inactive - "&$G18,IF($L18="","NO NEXT ACTION",IF(V18>0,"OVERDUE "&V18&"d",IF($L18-'Settings and Scoring Rules'!$B$4<='Settings and Scoring Rules'!$B$7,"DUE IN "&($L18-'Settings and Scoring Rules'!$B$4)&"d",IF(N(U18)>'Settings and Scoring Rules'!$B$8,"STALE","On track")))))) | X18: =IF($A18="","",$H18*M18*N18)
E19: =IF($D19="","",IFERROR(INDEX('Intermediary Directory'!$B$4:$B$28,MATCH($D19,'Intermediary Directory'!$A$4:$A$28,0)),"UNKNOWN ID")) | M19: =IF($A19="","",IFERROR(VLOOKUP($G19,'Settings and Scoring Rules'!$A$19:$D$28,3,FALSE),0)) | N19: =IF($A19="","",IFERROR(VLOOKUP($G19,'Settings and Scoring Rules'!$A$19:$D$28,4,FALSE),0)) | O19: =IF($A19="","",IF(AND($H19>='Settings and Scoring Rules'!$B$5,$H19<='Settings and Scoring Rules'!$B$6),1,IF(AND($H19>='Settings and Scoring Rules'!$B$5*0.5,$H19<='Settings and Scoring Rules'!$B$6*1.5),0.5,0))) | P19: =IF($A19="","",IFERROR(VLOOKUP($F19,'Settings and Scoring Rules'!$A$31:$B$33,2,FALSE),0)) | Q19: =IF($A19="","",IFERROR(INDEX('Intermediary Directory'!$H$4:$H$28,MATCH($D19,'Intermediary Directory'!$A$4:$A$28,0)),1)) | R19: =IF($A19="","",ROUND(100*('Settings and Scoring Rules'!$B$11*M19+'Settings and Scoring Rules'!$B$12*($I19-1)/4+'Settings and Scoring Rules'!$B$13*O19+'Settings and Scoring Rules'!$B$14*P19+'Settings and Scoring Rules'!$B$15*(Q19-1)/4),1)) | S19: =IF(OR($A19="",N19<>1),"",R19+(1000-ROW())/10^7) | T19: =IF(S19="","",COUNTIF($S$4:$S$43,">"&S19)+1) | U19: =IF(OR($A19="",$J19=""),"",'Settings and Scoring Rules'!$B$4-$J19) | V19: =IF(OR($A19="",N19<>1,$L19=""),"",MAX(0,'Settings and Scoring Rules'!$B$4-$L19)) | W19: =IF($A19="","",IF(N19<>1,"Inactive - "&$G19,IF($L19="","NO NEXT ACTION",IF(V19>0,"OVERDUE "&V19&"d",IF($L19-'Settings and Scoring Rules'!$B$4<='Settings and Scoring Rules'!$B$7,"DUE IN "&($L19-'Settings and Scoring Rules'!$B$4)&"d",IF(N(U19)>'Settings and Scoring Rules'!$B$8,"STALE","On track")))))) | X19: =IF($A19="","",$H19*M19*N19)
E20: =IF($D20="","",IFERROR(INDEX('Intermediary Directory'!$B$4:$B$28,MATCH($D20,'Intermediary Directory'!$A$4:$A$28,0)),"UNKNOWN ID")) | M20: =IF($A20="","",IFERROR(VLOOKUP($G20,'Settings and Scoring Rules'!$A$19:$D$28,3,FALSE),0)) | N20: =IF($A20="","",IFERROR(VLOOKUP($G20,'Settings and Scoring Rules'!$A$19:$D$28,4,FALSE),0)) | O20: =IF($A20="","",IF(AND($H20>='Settings and Scoring Rules'!$B$5,$H20<='Settings and Scoring Rules'!$B$6),1,IF(AND($H20>='Settings and Scoring Rules'!$B$5*0.5,$H20<='Settings and Scoring Rules'!$B$6*1.5),0.5,0))) | P20: =IF($A20="","",IFERROR(VLOOKUP($F20,'Settings and Scoring Rules'!$A$31:$B$33,2,FALSE),0)) | Q20: =IF($A20="","",IFERROR(INDEX('Intermediary Directory'!$H$4:$H$28,MATCH($D20,'Intermediary Directory'!$A$4:$A$28,0)),1)) | R20: =IF($A20="","",ROUND(100*('Settings and Scoring Rules'!$B$11*M20+'Settings and Scoring Rules'!$B$12*($I20-1)/4+'Settings and Scoring Rules'!$B$13*O20+'Settings and Scoring Rules'!$B$14*P20+'Settings and Scoring Rules'!$B$15*(Q20-1)/4),1)) | S20: =IF(OR($A20="",N20<>1),"",R20+(1000-ROW())/10^7) | T20: =IF(S20="","",COUNTIF($S$4:$S$43,">"&S20)+1) | U20: =IF(OR($A20="",$J20=""),"",'Settings and Scoring Rules'!$B$4-$J20) | V20: =IF(OR($A20="",N20<>1,$L20=""),"",MAX(0,'Settings and Scoring Rules'!$B$4-$L20)) | W20: =IF($A20="","",IF(N20<>1,"Inactive - "&$G20,IF($L20="","NO NEXT ACTION",IF(V20>0,"OVERDUE "&V20&"d",IF($L20-'Settings and Scoring Rules'!$B$4<='Settings and Scoring Rules'!$B$7,"DUE IN "&($L20-'Settings and Scoring Rules'!$B$4)&"d",IF(N(U20)>'Settings and Scoring Rules'!$B$8,"STALE","On track")))))) | X20: =IF($A20="","",$H20*M20*N20)
E21: =IF($D21="","",IFERROR(INDEX('Intermediary Directory'!$B$4:$B$28,MATCH($D21,'Intermediary Directory'!$A$4:$A$28,0)),"UNKNOWN ID")) | M21: =IF($A21="","",IFERROR(VLOOKUP($G21,'Settings and Scoring Rules'!$A$19:$D$28,3,FALSE),0)) | N21: =IF($A21="","",IFERROR(VLOOKUP($G21,'Settings and Scoring Rules'!$A$19:$D$28,4,FALSE),0)) | O21: =IF($A21="","",IF(AND($H21>='Settings and Scoring Rules'!$B$5,$H21<='Settings and Scoring Rules'!$B$6),1,IF(AND($H21>='Settings and Scoring Rules'!$B$5*0.5,$H21<='Settings and Scoring Rules'!$B$6*1.5),0.5,0))) | P21: =IF($A21="","",IFERROR(VLOOKUP($F21,'Settings and Scoring Rules'!$A$31:$B$33,2,FALSE),0)) | Q21: =IF($A21="","",IFERROR(INDEX('Intermediary Directory'!$H$4:$H$28,MATCH($D21,'Intermediary Directory'!$A$4:$A$28,0)),1)) | R21: =IF($A21="","",ROUND(100*('Settings and Scoring Rules'!$B$11*M21+'Settings and Scoring Rules'!$B$12*($I21-1)/4+'Settings and Scoring Rules'!$B$13*O21+'Settings and Scoring Rules'!$B$14*P21+'Settings and Scoring Rules'!$B$15*(Q21-1)/4),1)) | S21: =IF(OR($A21="",N21<>1),"",R21+(1000-ROW())/10^7) | T21: =IF(S21="","",COUNTIF($S$4:$S$43,">"&S21)+1) | U21: =IF(OR($A21="",$J21=""),"",'Settings and Scoring Rules'!$B$4-$J21) | V21: =IF(OR($A21="",N21<>1,$L21=""),"",MAX(0,'Settings and Scoring Rules'!$B$4-$L21)) | W21: =IF($A21="","",IF(N21<>1,"Inactive - "&$G21,IF($L21="","NO NEXT ACTION",IF(V21>0,"OVERDUE "&V21&"d",IF($L21-'Settings and Scoring Rules'!$B$4<='Settings and Scoring Rules'!$B$7,"DUE IN "&($L21-'Settings and Scoring Rules'!$B$4)&"d",IF(N(U21)>'Settings and Scoring Rules'!$B$8,"STALE","On track")))))) | X21: =IF($A21="","",$H21*M21*N21)
E22: =IF($D22="","",IFERROR(INDEX('Intermediary Directory'!$B$4:$B$28,MATCH($D22,'Intermediary Directory'!$A$4:$A$28,0)),"UNKNOWN ID")) | M22: =IF($A22="","",IFERROR(VLOOKUP($G22,'Settings and Scoring Rules'!$A$19:$D$28,3,FALSE),0)) | N22: =IF($A22="","",IFERROR(VLOOKUP($G22,'Settings and Scoring Rules'!$A$19:$D$28,4,FALSE),0)) | O22: =IF($A22="","",IF(AND($H22>='Settings and Scoring Rules'!$B$5,$H22<='Settings and Scoring Rules'!$B$6),1,IF(AND($H22>='Settings and Scoring Rules'!$B$5*0.5,$H22<='Settings and Scoring Rules'!$B$6*1.5),0.5,0))) | P22: =IF($A22="","",IFERROR(VLOOKUP($F22,'Settings and Scoring Rules'!$A$31:$B$33,2,FALSE),0)) | Q22: =IF($A22="","",IFERROR(INDEX('Intermediary Directory'!$H$4:$H$28,MATCH($D22,'Intermediary Directory'!$A$4:$A$28,0)),1)) | R22: =IF($A22="","",ROUND(100*('Settings and Scoring Rules'!$B$11*M22+'Settings and Scoring Rules'!$B$12*($I22-1)/4+'Settings and Scoring Rules'!$B$13*O22+'Settings and Scoring Rules'!$B$14*P22+'Settings and Scoring Rules'!$B$15*(Q22-1)/4),1)) | S22: =IF(OR($A22="",N22<>1),"",R22+(1000-ROW())/10^7) | T22: =IF(S22="","",COUNTIF($S$4:$S$43,">"&S22)+1) | U22: =IF(OR($A22="",$J22=""),"",'Settings and Scoring Rules'!$B$4-$J22) | V22: =IF(OR($A22="",N22<>1,$L22=""),"",MAX(0,'Settings and Scoring Rules'!$B$4-$L22)) | W22: =IF($A22="","",IF(N22<>1,"Inactive - "&$G22,IF($L22="","NO NEXT ACTION",IF(V22>0,"OVERDUE "&V22&"d",IF($L22-'Settings and Scoring Rules'!$B$4<='Settings and Scoring Rules'!$B$7,"DUE IN "&($L22-'Settings and Scoring Rules'!$B$4)&"d",IF(N(U22)>'Settings and Scoring Rules'!$B$8,"STALE","On track")))))) | X22: =IF($A22="","",$H22*M22*N22)
E23: =IF($D23="","",IFERROR(INDEX('Intermediary Directory'!$B$4:$B$28,MATCH($D23,'Intermediary Directory'!$A$4:$A$28,0)),"UNKNOWN ID")) | M23: =IF($A23="","",IFERROR(VLOOKUP($G23,'Settings and Scoring Rules'!$A$19:$D$28,3,FALSE),0)) | N23: =IF($A23="","",IFERROR(VLOOKUP($G23,'Settings and Scoring Rules'!$A$19:$D$28,4,FALSE),0)) | O23: =IF($A23="","",IF(AND($H23>='Settings and Scoring Rules'!$B$5,$H23<='Settings and Scoring Rules'!$B$6),1,IF(AND($H23>='Settings and Scoring Rules'!$B$5*0.5,$H23<='Settings and Scoring Rules'!$B$6*1.5),0.5,0))) | P23: =IF($A23="","",IFERROR(VLOOKUP($F23,'Settings and Scoring Rules'!$A$31:$B$33,2,FALSE),0)) | Q23: =IF($A23="","",IFERROR(INDEX('Intermediary Directory'!$H$4:$H$28,MATCH($D23,'Intermediary Directory'!$A$4:$A$28,0)),1)) | R23: =IF($A23="","",ROUND(100*('Settings and Scoring Rules'!$B$11*M23+'Settings and Scoring Rules'!$B$12*($I23-1)/4+'Settings and Scoring Rules'!$B$13*O23+'Settings and Scoring Rules'!$B$14*P23+'Settings and Scoring Rules'!$B$15*(Q23-1)/4),1)) | S23: =IF(OR($A23="",N23<>1),"",R23+(1000-ROW())/10^7) | T23: =IF(S23="","",COUNTIF($S$4:$S$43,">"&S23)+1) | U23: =IF(OR($A23="",$J23=""),"",'Settings and Scoring Rules'!$B$4-$J23) | V23: =IF(OR($A23="",N23<>1,$L23=""),"",MAX(0,'Settings and Scoring Rules'!$B$4-$L23)) | W23: =IF($A23="","",IF(N23<>1,"Inactive - "&$G23,IF($L23="","NO NEXT ACTION",IF(V23>0,"OVERDUE "&V23&"d",IF($L23-'Settings and Scoring Rules'!$B$4<='Settings and Scoring Rules'!$B$7,"DUE IN "&($L23-'Settings and Scoring Rules'!$B$4)&"d",IF(N(U23)>'Settings and Scoring Rules'!$B$8,"STALE","On track")))))) | X23: =IF($A23="","",$H23*M23*N23)
E24: =IF($D24="","",IFERROR(INDEX('Intermediary Directory'!$B$4:$B$28,MATCH($D24,'Intermediary Directory'!$A$4:$A$28,0)),"UNKNOWN ID")) | M24: =IF($A24="","",IFERROR(VLOOKUP($G24,'Settings and Scoring Rules'!$A$19:$D$28,3,FALSE),0)) | N24: =IF($A24="","",IFERROR(VLOOKUP($G24,'Settings and Scoring Rules'!$A$19:$D$28,4,FALSE),0)) | O24: =IF($A24="","",IF(AND($H24>='Settings and Scoring Rules'!$B$5,$H24<='Settings and Scoring Rules'!$B$6),1,IF(AND($H24>='Settings and Scoring Rules'!$B$5*0.5,$H24<='Settings and Scoring Rules'!$B$6*1.5),0.5,0))) | P24: =IF($A24="","",IFERROR(VLOOKUP($F24,'Settings and Scoring Rules'!$A$31:$B$33,2,FALSE),0)) | Q24: =IF($A24="","",IFERROR(INDEX('Intermediary Directory'!$H$4:$H$28,MATCH($D24,'Intermediary Directory'!$A$4:$A$28,0)),1)) | R24: =IF($A24="","",ROUND(100*('Settings and Scoring Rules'!$B$11*M24+'Settings and Scoring Rules'!$B$12*($I24-1)/4+'Settings and Scoring Rules'!$B$13*O24+'Settings and Scoring Rules'!$B$14*P24+'Settings and Scoring Rules'!$B$15*(Q24-1)/4),1)) | S24: =IF(OR($A24="",N24<>1),"",R24+(1000-ROW())/10^7) | T24: =IF(S24="","",COUNTIF($S$4:$S$43,">"&S24)+1) | U24: =IF(OR($A24="",$J24=""),"",'Settings and Scoring Rules'!$B$4-$J24) | V24: =IF(OR($A24="",N24<>1,$L24=""),"",MAX(0,'Settings and Scoring Rules'!$B$4-$L24)) | W24: =IF($A24="","",IF(N24<>1,"Inactive - "&$G24,IF($L24="","NO NEXT ACTION",IF(V24>0,"OVERDUE "&V24&"d",IF($L24-'Settings and Scoring Rules'!$B$4<='Settings and Scoring Rules'!$B$7,"DUE IN "&($L24-'Settings and Scoring Rules'!$B$4)&"d",IF(N(U24)>'Settings and Scoring Rules'!$B$8,"STALE","On track")))))) | X24: =IF($A24="","",$H24*M24*N24)
E25: =IF($D25="","",IFERROR(INDEX('Intermediary Directory'!$B$4:$B$28,MATCH($D25,'Intermediary Directory'!$A$4:$A$28,0)),"UNKNOWN ID")) | M25: =IF($A25="","",IFERROR(VLOOKUP($G25,'Settings and Scoring Rules'!$A$19:$D$28,3,FALSE),0)) | N25: =IF($A25="","",IFERROR(VLOOKUP($G25,'Settings and Scoring Rules'!$A$19:$D$28,4,FALSE),0)) | O25: =IF($A25="","",IF(AND($H25>='Settings and Scoring Rules'!$B$5,$H25<='Settings and Scoring Rules'!$B$6),1,IF(AND($H25>='Settings and Scoring Rules'!$B$5*0.5,$H25<='Settings and Scoring Rules'!$B$6*1.5),0.5,0))) | P25: =IF($A25="","",IFERROR(VLOOKUP($F25,'Settings and Scoring Rules'!$A$31:$B$33,2,FALSE),0)) | Q25: =IF($A25="","",IFERROR(INDEX('Intermediary Directory'!$H$4:$H$28,MATCH($D25,'Intermediary Directory'!$A$4:$A$28,0)),1)) | R25: =IF($A25="","",ROUND(100*('Settings and Scoring Rules'!$B$11*M25+'Settings and Scoring Rules'!$B$12*($I25-1)/4+'Settings and Scoring Rules'!$B$13*O25+'Settings and Scoring Rules'!$B$14*P25+'Settings and Scoring Rules'!$B$15*(Q25-1)/4),1)) | S25: =IF(OR($A25="",N25<>1),"",R25+(1000-ROW())/10^7) | T25: =IF(S25="","",COUNTIF($S$4:$S$43,">"&S25)+1) | U25: =IF(OR($A25="",$J25=""),"",'Settings and Scoring Rules'!$B$4-$J25) | V25: =IF(OR($A25="",N25<>1,$L25=""),"",MAX(0,'Settings and Scoring Rules'!$B$4-$L25)) | W25: =IF($A25="","",IF(N25<>1,"Inactive - "&$G25,IF($L25="","NO NEXT ACTION",IF(V25>0,"OVERDUE "&V25&"d",IF($L25-'Settings and Scoring Rules'!$B$4<='Settings and Scoring Rules'!$B$7,"DUE IN "&($L25-'Settings and Scoring Rules'!$B$4)&"d",IF(N(U25)>'Settings and Scoring Rules'!$B$8,"STALE","On track")))))) | X25: =IF($A25="","",$H25*M25*N25)
E26: =IF($D26="","",IFERROR(INDEX('Intermediary Directory'!$B$4:$B$28,MATCH($D26,'Intermediary Directory'!$A$4:$A$28,0)),"UNKNOWN ID")) | M26: =IF($A26="","",IFERROR(VLOOKUP($G26,'Settings and Scoring Rules'!$A$19:$D$28,3,FALSE),0)) | N26: =IF($A26="","",IFERROR(VLOOKUP($G26,'Settings and Scoring Rules'!$A$19:$D$28,4,FALSE),0)) | O26: =IF($A26="","",IF(AND($H26>='Settings and Scoring Rules'!$B$5,$H26<='Settings and Scoring Rules'!$B$6),1,IF(AND($H26>='Settings and Scoring Rules'!$B$5*0.5,$H26<='Settings and Scoring Rules'!$B$6*1.5),0.5,0))) | P26: =IF($A26="","",IFERROR(VLOOKUP($F26,'Settings and Scoring Rules'!$A$31:$B$33,2,FALSE),0)) | Q26: =IF($A26="","",IFERROR(INDEX('Intermediary Directory'!$H$4:$H$28,MATCH($D26,'Intermediary Directory'!$A$4:$A$28,0)),1)) | R26: =IF($A26="","",ROUND(100*('Settings and Scoring Rules'!$B$11*M26+'Settings and Scoring Rules'!$B$12*($I26-1)/4+'Settings and Scoring Rules'!$B$13*O26+'Settings and Scoring Rules'!$B$14*P26+'Settings and Scoring Rules'!$B$15*(Q26-1)/4),1)) | S26: =IF(OR($A26="",N26<>1),"",R26+(1000-ROW())/10^7) | T26: =IF(S26="","",COUNTIF($S$4:$S$43,">"&S26)+1) | U26: =IF(OR($A26="",$J26=""),"",'Settings and Scoring Rules'!$B$4-$J26) | V26: =IF(OR($A26="",N26<>1,$L26=""),"",MAX(0,'Settings and Scoring Rules'!$B$4-$L26)) | W26: =IF($A26="","",IF(N26<>1,"Inactive - "&$G26,IF($L26="","NO NEXT ACTION",IF(V26>0,"OVERDUE "&V26&"d",IF($L26-'Settings and Scoring Rules'!$B$4<='Settings and Scoring Rules'!$B$7,"DUE IN "&($L26-'Settings and Scoring Rules'!$B$4)&"d",IF(N(U26)>'Settings and Scoring Rules'!$B$8,"STALE","On track")))))) | X26: =IF($A26="","",$H26*M26*N26)
E27: =IF($D27="","",IFERROR(INDEX('Intermediary Directory'!$B$4:$B$28,MATCH($D27,'Intermediary Directory'!$A$4:$A$28,0)),"UNKNOWN ID")) | M27: =IF($A27="","",IFERROR(VLOOKUP($G27,'Settings and Scoring Rules'!$A$19:$D$28,3,FALSE),0)) | N27: =IF($A27="","",IFERROR(VLOOKUP($G27,'Settings and Scoring Rules'!$A$19:$D$28,4,FALSE),0)) | O27: =IF($A27="","",IF(AND($H27>='Settings and Scoring Rules'!$B$5,$H27<='Settings and Scoring Rules'!$B$6),1,IF(AND($H27>='Settings and Scoring Rules'!$B$5*0.5,$H27<='Settings and Scoring Rules'!$B$6*1.5),0.5,0))) | P27: =IF($A27="","",IFERROR(VLOOKUP($F27,'Settings and Scoring Rules'!$A$31:$B$33,2,FALSE),0)) | Q27: =IF($A27="","",IFERROR(INDEX('Intermediary Directory'!$H$4:$H$28,MATCH($D27,'Intermediary Directory'!$A$4:$A$28,0)),1)) | R27: =IF($A27="","",ROUND(100*('Settings and Scoring Rules'!$B$11*M27+'Settings and Scoring Rules'!$B$12*($I27-1)/4+'Settings and Scoring Rules'!$B$13*O27+'Settings and Scoring Rules'!$B$14*P27+'Settings and Scoring Rules'!$B$15*(Q27-1)/4),1)) | S27: =IF(OR($A27="",N27<>1),"",R27+(1000-ROW())/10^7) | T27: =IF(S27="","",COUNTIF($S$4:$S$43,">"&S27)+1) | U27: =IF(OR($A27="",$J27=""),"",'Settings and Scoring Rules'!$B$4-$J27) | V27: =IF(OR($A27="",N27<>1,$L27=""),"",MAX(0,'Settings and Scoring Rules'!$B$4-$L27)) | W27: =IF($A27="","",IF(N27<>1,"Inactive - "&$G27,IF($L27="","NO NEXT ACTION",IF(V27>0,"OVERDUE "&V27&"d",IF($L27-'Settings and Scoring Rules'!$B$4<='Settings and Scoring Rules'!$B$7,"DUE IN "&($L27-'Settings and Scoring Rules'!$B$4)&"d",IF(N(U27)>'Settings and Scoring Rules'!$B$8,"STALE","On track")))))) | X27: =IF($A27="","",$H27*M27*N27)
... E43: =IF($D43="","",IFERROR(INDEX('Intermediary Directory'!$B$4:$B$28,MATCH($D43,'Intermediary Directory'!$A$4:$A$28,0)),"UNKNOWN ID")) | M43: =IF($A43="","",IFERROR(VLOOKUP($G43,'Settings and Scoring Rules'!$A$19:$D$28,3,FALSE),0)) | N43: =IF($A43="","",IFERROR(VLOOKUP($G43,'Settings and Scoring Rules'!$A$19:$D$28,4,FALSE),0)) | O43: =IF($A43="","",IF(AND($H43>='Settings and Scoring Rules'!$B$5,$H43<='Settings and Scoring Rules'!$B$6),1,IF(AND($H43>='Settings and Scoring Rules'!$B$5*0.5,$H43<='Settings and Scoring Rules'!$B$6*1.5),0.5,0))) | P43: =IF($A43="","",IFERROR(VLOOKUP($F43,'Settings and Scoring Rules'!$A$31:$B$33,2,FALSE),0)) | Q43: =IF($A43="","",IFERROR(INDEX('Intermediary Directory'!$H$4:$H$28,MATCH($D43,'Intermediary Directory'!$A$4:$A$28,0)),1)) | R43: =IF($A43="","",ROUND(100*('Settings and Scoring Rules'!$B$11*M43+'Settings and Scoring Rules'!$B$12*($I43-1)/4+'Settings and Scoring Rules'!$B$13*O43+'Settings and Scoring Rules'!$B$14*P43+'Settings and Scoring Rules'!$B$15*(Q43-1)/4),1)) | S43: =IF(OR($A43="",N43<>1),"",R43+(1000-ROW())/10^7) | T43: =IF(S43="","",COUNTIF($S$4:$S$43,">"&S43)+1) | U43: =IF(OR($A43="",$J43=""),"",'Settings and Scoring Rules'!$B$4-$J43) | V43: =IF(OR($A43="",N43<>1,$L43=""),"",MAX(0,'Settings and Scoring Rules'!$B$4-$L43)) | W43: =IF($A43="","",IF(N43<>1,"Inactive - "&$G43,IF($L43="","NO NEXT ACTION",IF(V43>0,"OVERDUE "&V43&"d",IF($L43-'Settings and Scoring Rules'!$B$4<='Settings and Scoring Rules'!$B$7,"DUE IN "&($L43-'Settings and Scoring Rules'!$B$4)&"d",IF(N(U43)>'Settings and Scoring Rules'!$B$8,"STALE","On track")))))) | X43: =IF($A43="","",$H43*M43*N43)

Sheet Follow-Up Cadence Tracker
A1: Follow-Up Cadence Tracker
A2: Section A: intermediary touch cadence by tier. Section B: every deal's next action. All cells are live formulas.
A3: A. Intermediary touch cadence (one row per Intermediary Directory row)
A4: ID | B4: Code name | C4: Tier | D4: Cadence (days) | E4: Last contact | F4: Next touch due | G4: Days until due | H4: Days overdue | I4: Cadence flag | J4: Active deals | K4: Suggested action
A5: =IF('Intermediary Directory'!A4="","",'Intermediary Directory'!A4) -> I01 | B5: =IF(A5="","",'Intermediary Directory'!B4) -> Banker A | C5: =IF(A5="","",'Intermediary Directory'!G4) -> A | D5: =IF(A5="","",IFERROR(VLOOKUP(C5,'Settings and Scoring Rules'!$A$36:$B$38,2,FALSE),30)) -> 14 | E5: =IF(A5="","",'Intermediary Directory'!I4) -> 46293 | F5: =IF(A5="","",E5+D5) -> 46307 | G5: =IF(A5="","",F5-'Settings and Scoring Rules'!$B$4) -> 8 | H5: =IF(A5="","",MAX(0,-G5)) -> 0 | I5: =IF(A5="","",IF(H5>0,"OVERDUE "&H5&"d",IF(G5<='Settings and Scoring Rules'!$B$7,"DUE IN "&G5&"d","On track"))) -> On track | J5: =IF(A5="","",'Intermediary Directory'!L4) -> 1 | K5: =IF(A5="","",IF(H5>0,"Call this week",IF(G5<='Settings and Scoring Rules'!$B$7,"Touch by "&TEXT(F5,"yyyy-mm-dd"),"Next touch "&TEXT(F5,"yyyy-mm-dd")))) -> Next touch 2026-10-12
A6: =IF('Intermediary Directory'!A5="","",'Intermediary Directory'!A5) -> I02 | B6: =IF(A6="","",'Intermediary Directory'!B5) -> Banker B | C6: =IF(A6="","",'Intermediary Directory'!G5) -> A | D6: =IF(A6="","",IFERROR(VLOOKUP(C6,'Settings and Scoring Rules'!$A$36:$B$38,2,FALSE),30)) -> 14 | E6: =IF(A6="","",'Intermediary Directory'!I5) -> 46275 | F6: =IF(A6="","",E6+D6) -> 46289 | G6: =IF(A6="","",F6-'Settings and Scoring Rules'!$B$4) -> -10 | H6: =IF(A6="","",MAX(0,-G6)) -> 10 | I6: =IF(A6="","",IF(H6>0,"OVERDUE "&H6&"d",IF(G6<='Settings and Scoring Rules'!$B$7,"DUE IN "&G6&"d","On track"))) -> OVERDUE 10d | J6: =IF(A6="","",'Intermediary Directory'!L5) -> 1 | K6: =IF(A6="","",IF(H6>0,"Call this week",IF(G6<='Settings and Scoring Rules'!$B$7,"Touch by "&TEXT(F6,"yyyy-mm-dd"),"Next touch "&TEXT(F6,"yyyy-mm-dd")))) -> Call this week
A7: =IF('Intermediary Directory'!A6="","",'Intermediary Directory'!A6) -> I03 | B7: =IF(A7="","",'Intermediary Directory'!B6) -> Broker C | C7: =IF(A7="","",'Intermediary Directory'!G6) -> B | D7: =IF(A7="","",IFERROR(VLOOKUP(C7,'Settings and Scoring Rules'!$A$36:$B$38,2,FALSE),30)) -> 30 | E7: =IF(A7="","",'Intermediary Directory'!I6) -> 46254 | F7: =IF(A7="","",E7+D7) -> 46284 | G7: =IF(A7="","",F7-'Settings and Scoring Rules'!$B$4) -> -15 | H7: =IF(A7="","",MAX(0,-G7)) -> 15 | I7: =IF(A7="","",IF(H7>0,"OVERDUE "&H7&"d",IF(G7<='Settings and Scoring Rules'!$B$7,"DUE IN "&G7&"d","On track"))) -> OVERDUE 15d | J7: =IF(A7="","",'Intermediary Directory'!L6) -> 2 | K7: =IF(A7="","",IF(H7>0,"Call this week",IF(G7<='Settings and Scoring Rules'!$B$7,"Touch by "&TEXT(F7,"yyyy-mm-dd"),"Next touch "&TEXT(F7,"yyyy-mm-dd")))) -> Call this week
A8: =IF('Intermediary Directory'!A7="","",'Intermediary Directory'!A7) -> I04 | B8: =IF(A8="","",'Intermediary Directory'!B7) -> Broker D | C8: =IF(A8="","",'Intermediary Directory'!G7) -> B | D8: =IF(A8="","",IFERROR(VLOOKUP(C8,'Settings and Scoring Rules'!$A$36:$B$38,2,FALSE),30)) -> 30 | E8: =IF(A8="","",'Intermediary Directory'!I7) -> 46287 | F8: =IF(A8="","",E8+D8) -> 46317 | G8: =IF(A8="","",F8-'Settings and Scoring Rules'!$B$4) -> 18 | H8: =IF(A8="","",MAX(0,-G8)) -> 0 | I8: =IF(A8="","",IF(H8>0,"OVERDUE "&H8&"d",IF(G8<='Settings and Scoring Rules'!$B$7,"DUE IN "&G8&"d","On track"))) -> On track | J8: =IF(A8="","",'Intermediary Directory'!L7) -> 1 | K8: =IF(A8="","",IF(H8>0,"Call this week",IF(G8<='Settings and Scoring Rules'!$B$7,"Touch by "&TEXT(F8,"yyyy-mm-dd"),"Next touch "&TEXT(F8,"yyyy-mm-dd")))) -> Next touch 2026-10-22
A9: =IF('Intermediary Directory'!A8="","",'Intermediary Directory'!A8) -> I05 | B9: =IF(A9="","",'Intermediary Directory'!B8) -> Advisor E | C9: =IF(A9="","",'Intermediary Directory'!G8) -> A | D9: =IF(A9="","",IFERROR(VLOOKUP(C9,'Settings and Scoring Rules'!$A$36:$B$38,2,FALSE),30)) -> 14 | E9: =IF(A9="","",'Intermediary Directory'!I8) -> 46288 | F9: =IF(A9="","",E9+D9) -> 46302 | G9: =IF(A9="","",F9-'Settings and Scoring Rules'!$B$4) -> 3 | H9: =IF(A9="","",MAX(0,-G9)) -> 0 | I9: =IF(A9="","",IF(H9>0,"OVERDUE "&H9&"d",IF(G9<='Settings and Scoring Rules'!$B$7,"DUE IN "&G9&"d","On track"))) -> DUE IN 3d | J9: =IF(A9="","",'Intermediary Directory'!L8) -> 1 | K9: =IF(A9="","",IF(H9>0,"Call this week",IF(G9<='Settings and Scoring Rules'!$B$7,"Touch by "&TEXT(F9,"yyyy-mm-dd"),"Next touch "&TEXT(F9,"yyyy-mm-dd")))) -> Touch by 2026-10-07
A10: =IF('Intermediary Directory'!A9="","",'Intermediary Directory'!A9) -> I06 | B10: =IF(A10="","",'Intermediary Directory'!B9) -> CPA F | C10: =IF(A10="","",'Intermediary Directory'!G9) -> C | D10: =IF(A10="","",IFERROR(VLOOKUP(C10,'Settings and Scoring Rules'!$A$36:$B$38,2,FALSE),30)) -> 60 | E10: =IF(A10="","",'Intermediary Directory'!I9) -> 46218 | F10: =IF(A10="","",E10+D10) -> 46278 | G10: =IF(A10="","",F10-'Settings and Scoring Rules'!$B$4) -> -21 | H10: =IF(A10="","",MAX(0,-G10)) -> 21 | I10: =IF(A10="","",IF(H10>0,"OVERDUE "&H10&"d",IF(G10<='Settings and Scoring Rules'!$B$7,"DUE IN "&G10&"d","On track"))) -> OVERDUE 21d | J10: =IF(A10="","",'Intermediary Directory'!L9) -> 1 | K10: =IF(A10="","",IF(H10>0,"Call this week",IF(G10<='Settings and Scoring Rules'!$B$7,"Touch by "&TEXT(F10,"yyyy-mm-dd"),"Next touch "&TEXT(F10,"yyyy-mm-dd")))) -> Call this week
A11: =IF('Intermediary Directory'!A10="","",'Intermediary Directory'!A10) -> I07 | B11: =IF(A11="","",'Intermediary Directory'!B10) -> Attorney G | C11: =IF(A11="","",'Intermediary Directory'!G10) -> C | D11: =IF(A11="","",IFERROR(VLOOKUP(C11,'Settings and Scoring Rules'!$A$36:$B$38,2,FALSE),30)) -> 60 | E11: =IF(A11="","",'Intermediary Directory'!I10) -> 46266 | F11: =IF(A11="","",E11+D11) -> 46326 | G11: =IF(A11="","",F11-'Settings and Scoring Rules'!$B$4) -> 27 | H11: =IF(A11="","",MAX(0,-G11)) -> 0 | I11: =IF(A11="","",IF(H11>0,"OVERDUE "&H11&"d",IF(G11<='Settings and Scoring Rules'!$B$7,"DUE IN "&G11&"d","On track"))) -> On track | J11: =IF(A11="","",'Intermediary Directory'!L10) -> 1 | K11: =IF(A11="","",IF(H11>0,"Call this week",IF(G11<='Settings and Scoring Rules'!$B$7,"Touch by "&TEXT(F11,"yyyy-mm-dd"),"Next touch "&TEXT(F11,"yyyy-mm-dd")))) -> Next touch 2026-10-31
A12: =IF('Intermediary Directory'!A11="","",'Intermediary Directory'!A11) -> I08 | B12: =IF(A12="","",'Intermediary Directory'!B11) -> Operator H | C12: =IF(A12="","",'Intermediary Directory'!G11) -> B | D12: =IF(A12="","",IFERROR(VLOOKUP(C12,'Settings and Scoring Rules'!$A$36:$B$38,2,FALSE),30)) -> 30 | E12: =IF(A12="","",'Intermediary Directory'!I11) -> 46295 | F12: =IF(A12="","",E12+D12) -> 46325 | G12: =IF(A12="","",F12-'Settings and Scoring Rules'!$B$4) -> 26 | H12: =IF(A12="","",MAX(0,-G12)) -> 0 | I12: =IF(A12="","",IF(H12>0,"OVERDUE "&H12&"d",IF(G12<='Settings and Scoring Rules'!$B$7,"DUE IN "&G12&"d","On track"))) -> On track | J12: =IF(A12="","",'Intermediary Directory'!L11) -> 1 | K12: =IF(A12="","",IF(H12>0,"Call this week",IF(G12<='Settings and Scoring Rules'!$B$7,"Touch by "&TEXT(F12,"yyyy-mm-dd"),"Next touch "&TEXT(F12,"yyyy-mm-dd")))) -> Next touch 2026-10-30
A13: =IF('Intermediary Directory'!A12="","",'Intermediary Directory'!A12) -> I09 | B13: =IF(A13="","",'Intermediary Directory'!B12) -> Banker I | C13: =IF(A13="","",'Intermediary Directory'!G12) -> B | D13: =IF(A13="","",IFERROR(VLOOKUP(C13,'Settings and Scoring Rules'!$A$36:$B$38,2,FALSE),30)) -> 30 | E13: =IF(A13="","",'Intermediary Directory'!I12) -> 46203 | F13: =IF(A13="","",E13+D13) -> 46233 | G13: =IF(A13="","",F13-'Settings and Scoring Rules'!$B$4) -> -66 | H13: =IF(A13="","",MAX(0,-G13)) -> 66 | I13: =IF(A13="","",IF(H13>0,"OVERDUE "&H13&"d",IF(G13<='Settings and Scoring Rules'!$B$7,"DUE IN "&G13&"d","On track"))) -> OVERDUE 66d | J13: =IF(A13="","",'Intermediary Directory'!L12) -> 0 | K13: =IF(A13="","",IF(H13>0,"Call this week",IF(G13<='Settings and Scoring Rules'!$B$7,"Touch by "&TEXT(F13,"yyyy-mm-dd"),"Next touch "&TEXT(F13,"yyyy-mm-dd")))) -> Call this week
A14: =IF('Intermediary Directory'!A13="","",'Intermediary Directory'!A13) -> I10 | B14: =IF(A14="","",'Intermediary Directory'!B13) -> Founder J | C14: =IF(A14="","",'Intermediary Directory'!G13) -> C | D14: =IF(A14="","",IFERROR(VLOOKUP(C14,'Settings and Scoring Rules'!$A$36:$B$38,2,FALSE),30)) -> 60 | E14: =IF(A14="","",'Intermediary Directory'!I13) -> 46280 | F14: =IF(A14="","",E14+D14) -> 46340 | G14: =IF(A14="","",F14-'Settings and Scoring Rules'!$B$4) -> 41 | H14: =IF(A14="","",MAX(0,-G14)) -> 0 | I14: =IF(A14="","",IF(H14>0,"OVERDUE "&H14&"d",IF(G14<='Settings and Scoring Rules'!$B$7,"DUE IN "&G14&"d","On track"))) -> On track | J14: =IF(A14="","",'Intermediary Directory'!L13) -> 1 | K14: =IF(A14="","",IF(H14>0,"Call this week",IF(G14<='Settings and Scoring Rules'!$B$7,"Touch by "&TEXT(F14,"yyyy-mm-dd"),"Next touch "&TEXT(F14,"yyyy-mm-dd")))) -> Next touch 2026-11-14
A15: =IF('Intermediary Directory'!A14="","",'Intermediary Directory'!A14) | B15: =IF(A15="","",'Intermediary Directory'!B14) | C15: =IF(A15="","",'Intermediary Directory'!G14) | D15: =IF(A15="","",IFERROR(VLOOKUP(C15,'Settings and Scoring Rules'!$A$36:$B$38,2,FALSE),30)) | E15: =IF(A15="","",'Intermediary Directory'!I14) | F15: =IF(A15="","",E15+D15) | G15: =IF(A15="","",F15-'Settings and Scoring Rules'!$B$4) | H15: =IF(A15="","",MAX(0,-G15)) | I15: =IF(A15="","",IF(H15>0,"OVERDUE "&H15&"d",IF(G15<='Settings and Scoring Rules'!$B$7,"DUE IN "&G15&"d","On track"))) | J15: =IF(A15="","",'Intermediary Directory'!L14) | K15: =IF(A15="","",IF(H15>0,"Call this week",IF(G15<='Settings and Scoring Rules'!$B$7,"Touch by "&TEXT(F15,"yyyy-mm-dd"),"Next touch "&TEXT(F15,"yyyy-mm-dd"))))
A16: =IF('Intermediary Directory'!A15="","",'Intermediary Directory'!A15) | B16: =IF(A16="","",'Intermediary Directory'!B15) | C16: =IF(A16="","",'Intermediary Directory'!G15) | D16: =IF(A16="","",IFERROR(VLOOKUP(C16,'Settings and Scoring Rules'!$A$36:$B$38,2,FALSE),30)) | E16: =IF(A16="","",'Intermediary Directory'!I15) | F16: =IF(A16="","",E16+D16) | G16: =IF(A16="","",F16-'Settings and Scoring Rules'!$B$4) | H16: =IF(A16="","",MAX(0,-G16)) | I16: =IF(A16="","",IF(H16>0,"OVERDUE "&H16&"d",IF(G16<='Settings and Scoring Rules'!$B$7,"DUE IN "&G16&"d","On track"))) | J16: =IF(A16="","",'Intermediary Directory'!L15) | K16: =IF(A16="","",IF(H16>0,"Call this week",IF(G16<='Settings and Scoring Rules'!$B$7,"Touch by "&TEXT(F16,"yyyy-mm-dd"),"Next touch "&TEXT(F16,"yyyy-mm-dd"))))
... A29: =IF('Intermediary Directory'!A28="","",'Intermediary Directory'!A28) | B29: =IF(A29="","",'Intermediary Directory'!B28) | C29: =IF(A29="","",'Intermediary Directory'!G28) | D29: =IF(A29="","",IFERROR(VLOOKUP(C29,'Settings and Scoring Rules'!$A$36:$B$38,2,FALSE),30)) | E29: =IF(A29="","",'Intermediary Directory'!I28) | F29: =IF(A29="","",E29+D29) | G29: =IF(A29="","",F29-'Settings and Scoring Rules'!$B$4) | H29: =IF(A29="","",MAX(0,-G29)) | I29: =IF(A29="","",IF(H29>0,"OVERDUE "&H29&"d",IF(G29<='Settings and Scoring Rules'!$B$7,"DUE IN "&G29&"d","On track"))) | J29: =IF(A29="","",'Intermediary Directory'!L28) | K29: =IF(A29="","",IF(H29>0,"Call this week",IF(G29<='Settings and Scoring Rules'!$B$7,"Touch by "&TEXT(F29,"yyyy-mm-dd"),"Next touch "&TEXT(F29,"yyyy-mm-dd"))))
A31: B. Deal next-action follow-ups (one row per Deal Pipeline Log row)
A32: Deal ID | B32: Code name | C32: Intermediary | D32: Stage | E32: Next action | F32: Next action due | G32: Days overdue | H32: Follow-up flag
A33: =IF('Deal Pipeline Log'!A4="","",'Deal Pipeline Log'!A4) -> D01 | B33: =IF(A33="","",'Deal Pipeline Log'!B4) -> Project Atlas | C33: =IF(A33="","",'Deal Pipeline Log'!E4) -> Banker A | D33: =IF(A33="","",'Deal Pipeline Log'!G4) -> Management Meeting | E33: =IF(A33="","",'Deal Pipeline Log'!K4) -> Send diligence request list | F33: =IF(A33="","",IF('Deal Pipeline Log'!L4="","",'Deal Pipeline Log'!L4)) -> 46303 | G33: =IF(A33="","",'Deal Pipeline Log'!V4) -> 0 | H33: =IF(A33="","",'Deal Pipeline Log'!W4) -> DUE IN 4d
A34: =IF('Deal Pipeline Log'!A5="","",'Deal Pipeline Log'!A5) -> D02 | B34: =IF(A34="","",'Deal Pipeline Log'!B5) -> Project Birch | C34: =IF(A34="","",'Deal Pipeline Log'!E5) -> Banker B | D34: =IF(A34="","",'Deal Pipeline Log'!G5) -> IOI Submitted | E34: =IF(A34="","",'Deal Pipeline Log'!K5) -> Follow up on IOI feedback | F34: =IF(A34="","",IF('Deal Pipeline Log'!L5="","",'Deal Pipeline Log'!L5)) -> 46294 | G34: =IF(A34="","",'Deal Pipeline Log'!V5) -> 5 | H34: =IF(A34="","",'Deal Pipeline Log'!W5) -> OVERDUE 5d
A35: =IF('Deal Pipeline Log'!A6="","",'Deal Pipeline Log'!A6) -> D03 | B35: =IF(A35="","",'Deal Pipeline Log'!B6) -> Project Cedar | C35: =IF(A35="","",'Deal Pipeline Log'!E6) -> Broker C | D35: =IF(A35="","",'Deal Pipeline Log'!G6) -> CIM Review | E35: =IF(A35="","",'Deal Pipeline Log'!K6) -> Call owner re: Q3 financials | F35: =IF(A35="","",IF('Deal Pipeline Log'!L6="","",'Deal Pipeline Log'!L6)) -> 46291 | G35: =IF(A35="","",'Deal Pipeline Log'!V6) -> 8 | H35: =IF(A35="","",'Deal Pipeline Log'!W6) -> OVERDUE 8d
A36: =IF('Deal Pipeline Log'!A7="","",'Deal Pipeline Log'!A7) -> D04 | B36: =IF(A36="","",'Deal Pipeline Log'!B7) -> Project Delta | C36: =IF(A36="","",'Deal Pipeline Log'!E7) -> Broker D | D36: =IF(A36="","",'Deal Pipeline Log'!G7) -> NDA / Teaser | E36: =IF(A36="","",'Deal Pipeline Log'!K7) -> Sign NDA and request CIM | F36: =IF(A36="","",IF('Deal Pipeline Log'!L7="","",'Deal Pipeline Log'!L7)) -> 46298 | G36: =IF(A36="","",'Deal Pipeline Log'!V7) -> 1 | H36: =IF(A36="","",'Deal Pipeline Log'!W7) -> OVERDUE 1d
A37: =IF('Deal Pipeline Log'!A8="","",'Deal Pipeline Log'!A8) -> D05 | B37: =IF(A37="","",'Deal Pipeline Log'!B8) -> Project Ember | C37: =IF(A37="","",'Deal Pipeline Log'!E8) -> Advisor E | D37: =IF(A37="","",'Deal Pipeline Log'!G8) -> CIM Review | E37: =IF(A37="","",'Deal Pipeline Log'!K8) -> Decide IOI go / no-go | F37: =IF(A37="","",IF('Deal Pipeline Log'!L8="","",'Deal Pipeline Log'!L8)) -> 46305 | G37: =IF(A37="","",'Deal Pipeline Log'!V8) -> 0 | H37: =IF(A37="","",'Deal Pipeline Log'!W8) -> DUE IN 6d
A38: =IF('Deal Pipeline Log'!A9="","",'Deal Pipeline Log'!A9) -> D06 | B38: =IF(A38="","",'Deal Pipeline Log'!B9) -> Project Falcon | C38: =IF(A38="","",'Deal Pipeline Log'!E9) -> Operator H | D38: =IF(A38="","",'Deal Pipeline Log'!G9) -> LOI Submitted | E38: =IF(A38="","",'Deal Pipeline Log'!K9) -> Negotiate LOI exclusivity terms | F38: =IF(A38="","",IF('Deal Pipeline Log'!L9="","",'Deal Pipeline Log'!L9)) -> 46301 | G38: =IF(A38="","",'Deal Pipeline Log'!V9) -> 0 | H38: =IF(A38="","",'Deal Pipeline Log'!W9) -> DUE IN 2d
A39: =IF('Deal Pipeline Log'!A10="","",'Deal Pipeline Log'!A10) -> D07 | B39: =IF(A39="","",'Deal Pipeline Log'!B10) -> Project Granite | C39: =IF(A39="","",'Deal Pipeline Log'!E10) -> CPA F | D39: =IF(A39="","",'Deal Pipeline Log'!G10) -> Sourced | E39: =IF(A39="","",'Deal Pipeline Log'!K10) -> Schedule intro call with owner | F39: =IF(A39="","",IF('Deal Pipeline Log'!L10="","",'Deal Pipeline Log'!L10)) -> 46280 | G39: =IF(A39="","",'Deal Pipeline Log'!V10) -> 19 | H39: =IF(A39="","",'Deal Pipeline Log'!W10) -> OVERDUE 19d
A40: =IF('Deal Pipeline Log'!A11="","",'Deal Pipeline Log'!A11) -> D08 | B40: =IF(A40="","",'Deal Pipeline Log'!B11) -> Project Harbor | C40: =IF(A40="","",'Deal Pipeline Log'!E11) -> Banker I | D40: =IF(A40="","",'Deal Pipeline Log'!G11) -> Passed | E40: =IF(A40="","",'Deal Pipeline Log'!K11) -> Passed - valuation gap | F40: =IF(A40="","",IF('Deal Pipeline Log'!L11="","",'Deal Pipeline Log'!L11)) | G40: =IF(A40="","",'Deal Pipeline Log'!V11) | H40: =IF(A40="","",'Deal Pipeline Log'!W11) -> Inactive - Passed
A41: =IF('Deal Pipeline Log'!A12="","",'Deal Pipeline Log'!A12) -> D09 | B41: =IF(A41="","",'Deal Pipeline Log'!B12) -> Project Iris | C41: =IF(A41="","",'Deal Pipeline Log'!E12) -> Founder J | D41: =IF(A41="","",'Deal Pipeline Log'!G12) -> Sourced | E41: =IF(A41="","",'Deal Pipeline Log'!K12) -> Request financial summary | F41: =IF(A41="","",IF('Deal Pipeline Log'!L12="","",'Deal Pipeline Log'!L12)) -> 46307 | G41: =IF(A41="","",'Deal Pipeline Log'!V12) -> 0 | H41: =IF(A41="","",'Deal Pipeline Log'!W12) -> On track
A42: =IF('Deal Pipeline Log'!A13="","",'Deal Pipeline Log'!A13) -> D10 | B42: =IF(A42="","",'Deal Pipeline Log'!B13) -> Project Juniper | C42: =IF(A42="","",'Deal Pipeline Log'!E13) -> Attorney G | D42: =IF(A42="","",'Deal Pipeline Log'!G13) -> IOI Submitted | E42: =IF(A42="","",'Deal Pipeline Log'!K13) -> Prepare management meeting questions | F42: =IF(A42="","",IF('Deal Pipeline Log'!L13="","",'Deal Pipeline Log'!L13)) -> 46304 | G42: =IF(A42="","",'Deal Pipeline Log'!V13) -> 0 | H42: =IF(A42="","",'Deal Pipeline Log'!W13) -> DUE IN 5d
A43: =IF('Deal Pipeline Log'!A14="","",'Deal Pipeline Log'!A14) -> D11 | B43: =IF(A43="","",'Deal Pipeline Log'!B14) -> Project Kestrel | C43: =IF(A43="","",'Deal Pipeline Log'!E14) -> Broker D | D43: =IF(A43="","",'Deal Pipeline Log'!G14) -> Lost | E43: =IF(A43="","",'Deal Pipeline Log'!K14) -> Lost - outbid | F43: =IF(A43="","",IF('Deal Pipeline Log'!L14="","",'Deal Pipeline Log'!L14)) | G43: =IF(A43="","",'Deal Pipeline Log'!V14) | H43: =IF(A43="","",'Deal Pipeline Log'!W14) -> Inactive - Lost
A44: =IF('Deal Pipeline Log'!A15="","",'Deal Pipeline Log'!A15) -> D12 | B44: =IF(A44="","",'Deal Pipeline Log'!B15) -> Project Larch | C44: =IF(A44="","",'Deal Pipeline Log'!E15) -> Broker C | D44: =IF(A44="","",'Deal Pipeline Log'!G15) -> NDA / Teaser | E44: =IF(A44="","",'Deal Pipeline Log'!K15) -> Review teaser vs thesis | F44: =IF(A44="","",IF('Deal Pipeline Log'!L15="","",'Deal Pipeline Log'!L15)) -> 46309 | G44: =IF(A44="","",'Deal Pipeline Log'!V15) -> 0 | H44: =IF(A44="","",'Deal Pipeline Log'!W15) -> On track
... A72: =IF('Deal Pipeline Log'!A43="","",'Deal Pipeline Log'!A43) | B72: =IF(A72="","",'Deal Pipeline Log'!B43) | C72: =IF(A72="","",'Deal Pipeline Log'!E43) | D72: =IF(A72="","",'Deal Pipeline Log'!G43) | E72: =IF(A72="","",'Deal Pipeline Log'!K43) | F72: =IF(A72="","",IF('Deal Pipeline Log'!L43="","",'Deal Pipeline Log'!L43)) | G72: =IF(A72="","",'Deal Pipeline Log'!V43) | H72: =IF(A72="","",'Deal Pipeline Log'!W43)

Sheet Ranking Dashboard
A1: Ranking Dashboard
A2: Live summary: pipeline KPIs, top-ranked active deals, stage funnel, most overdue follow-ups and one dashboard output line.
A3: Metric | B3: Value | C3: Source
A4: As-of date | B4: ='Settings and Scoring Rules'!$B$4 -> 46299 | C4: Settings B4
A5: Intermediaries tracked | B5: =COUNTA('Intermediary Directory'!$A$4:$A$28) -> 10 | C5: Intermediary Directory A4:A28
A6: Deals logged | B6: =COUNTA('Deal Pipeline Log'!$A$4:$A$43) -> 12 | C6: Deal Pipeline Log A4:A43
A7: Active deals | B7: =SUM('Deal Pipeline Log'!$N$4:$N$43) -> 10 | C7: Pipeline N
A8: Inactive deals (passed / lost / closed) | B8: =B6-B7 -> 2 | C8: Logged - active
A9: Active deals inside EBITDA band | B9: =COUNTIFS('Deal Pipeline Log'!$N$4:$N$43,1,'Deal Pipeline Log'!$O$4:$O$43,1) -> 8 | C9: Pipeline N and O
A10: Probability-weighted active EBITDA ($M) | B10: =SUM('Deal Pipeline Log'!$X$4:$X$43) -> 21.98 | C10: Pipeline X
A11: Overdue deal next actions | B11: =COUNTIF('Deal Pipeline Log'!$W$4:$W$43,"OVERDUE*") -> 4 | C11: Pipeline W
A12: Overdue intermediary touches | B12: =COUNTIF('Follow-Up Cadence Tracker'!$I$5:$I$29,"OVERDUE*") -> 4 | C12: Tracker I5:I29
A13: Follow-ups due within window | B13: =COUNTIF('Deal Pipeline Log'!$W$4:$W$43,"DUE IN*")+COUNTIF('Follow-Up Cadence Tracker'!$I$5:$I$29,"DUE IN*") -> 5 | C13: Pipeline W + Tracker I
A14: Stale active deals / missing next action | B14: =COUNTIF('Deal Pipeline Log'!$W$4:$W$43,"STALE")+COUNTIF('Deal Pipeline Log'!$W$4:$W$43,"NO NEXT ACTION") -> 0 | C14: Pipeline W
A15: Pipeline health | B15: =IF(B11+B12=0,"HEALTHY - no overdue follow-ups",IF(B11+B12<=3,"ATTENTION - clear overdue follow-ups this week","AT RISK - "&(B11+B12)&" overdue follow-ups; clear backlog before new outreach")) -> AT RISK - 8 overdue follow-ups; clear backlog before new outreach | C15: B11 + B12 gates
A17: Top 5 active deals by priority score
A18: Rank | B18: Deal | C18: Priority score | D18: Stage | E18: Intermediary | F18: Follow-up flag
A19: 1 | B19: =IFERROR(INDEX('Deal Pipeline Log'!$B$4:$B$43,MATCH($A19,'Deal Pipeline Log'!$T$4:$T$43,0)),"-") -> Project Falcon | C19: =IFERROR(INDEX('Deal Pipeline Log'!$R$4:$R$43,MATCH($A19,'Deal Pipeline Log'!$T$4:$T$43,0)),"-") -> 91 | D19: =IFERROR(INDEX('Deal Pipeline Log'!$G$4:$G$43,MATCH($A19,'Deal Pipeline Log'!$T$4:$T$43,0)),"-") -> LOI Submitted | E19: =IFERROR(INDEX('Deal Pipeline Log'!$E$4:$E$43,MATCH($A19,'Deal Pipeline Log'!$T$4:$T$43,0)),"-") -> Operator H | F19: =IFERROR(INDEX('Deal Pipeline Log'!$W$4:$W$43,MATCH($A19,'Deal Pipeline Log'!$T$4:$T$43,0)),"-") -> DUE IN 2d
A20: 2 | B20: =IFERROR(INDEX('Deal Pipeline Log'!$B$4:$B$43,MATCH($A20,'Deal Pipeline Log'!$T$4:$T$43,0)),"-") -> Project Atlas | C20: =IFERROR(INDEX('Deal Pipeline Log'!$R$4:$R$43,MATCH($A20,'Deal Pipeline Log'!$T$4:$T$43,0)),"-") -> 79 | D20: =IFERROR(INDEX('Deal Pipeline Log'!$G$4:$G$43,MATCH($A20,'Deal Pipeline Log'!$T$4:$T$43,0)),"-") -> Management Meeting | E20: =IFERROR(INDEX('Deal Pipeline Log'!$E$4:$E$43,MATCH($A20,'Deal Pipeline Log'!$T$4:$T$43,0)),"-") -> Banker A | F20: =IFERROR(INDEX('Deal Pipeline Log'!$W$4:$W$43,MATCH($A20,'Deal Pipeline Log'!$T$4:$T$43,0)),"-") -> DUE IN 4d
A21: 3 | B21: =IFERROR(INDEX('Deal Pipeline Log'!$B$4:$B$43,MATCH($A21,'Deal Pipeline Log'!$T$4:$T$43,0)),"-") -> Project Cedar | C21: =IFERROR(INDEX('Deal Pipeline Log'!$R$4:$R$43,MATCH($A21,'Deal Pipeline Log'!$T$4:$T$43,0)),"-") -> 63.5 | D21: =IFERROR(INDEX('Deal Pipeline Log'!$G$4:$G$43,MATCH($A21,'Deal Pipeline Log'!$T$4:$T$43,0)),"-") -> CIM Review | E21: =IFERROR(INDEX('Deal Pipeline Log'!$E$4:$E$43,MATCH($A21,'Deal Pipeline Log'!$T$4:$T$43,0)),"-") -> Broker C | F21: =IFERROR(INDEX('Deal Pipeline Log'!$W$4:$W$43,MATCH($A21,'Deal Pipeline Log'!$T$4:$T$43,0)),"-") -> OVERDUE 8d
A22: 4 | B22: =IFERROR(INDEX('Deal Pipeline Log'!$B$4:$B$43,MATCH($A22,'Deal Pipeline Log'!$T$4:$T$43,0)),"-") -> Project Juniper | C22: =IFERROR(INDEX('Deal Pipeline Log'!$R$4:$R$43,MATCH($A22,'Deal Pipeline Log'!$T$4:$T$43,0)),"-") -> 62 | D22: =IFERROR(INDEX('Deal Pipeline Log'!$G$4:$G$43,MATCH($A22,'Deal Pipeline Log'!$T$4:$T$43,0)),"-") -> IOI Submitted | E22: =IFERROR(INDEX('Deal Pipeline Log'!$E$4:$E$43,MATCH($A22,'Deal Pipeline Log'!$T$4:$T$43,0)),"-") -> Attorney G | F22: =IFERROR(INDEX('Deal Pipeline Log'!$W$4:$W$43,MATCH($A22,'Deal Pipeline Log'!$T$4:$T$43,0)),"-") -> DUE IN 5d
A23: 5 | B23: =IFERROR(INDEX('Deal Pipeline Log'!$B$4:$B$43,MATCH($A23,'Deal Pipeline Log'!$T$4:$T$43,0)),"-") -> Project Iris | C23: =IFERROR(INDEX('Deal Pipeline Log'!$R$4:$R$43,MATCH($A23,'Deal Pipeline Log'!$T$4:$T$43,0)),"-") -> 61.5 | D23: =IFERROR(INDEX('Deal Pipeline Log'!$G$4:$G$43,MATCH($A23,'Deal Pipeline Log'!$T$4:$T$43,0)),"-") -> Sourced | E23: =IFERROR(INDEX('Deal Pipeline Log'!$E$4:$E$43,MATCH($A23,'Deal Pipeline Log'!$T$4:$T$43,0)),"-") -> Founder J | F23: =IFERROR(INDEX('Deal Pipeline Log'!$W$4:$W$43,MATCH($A23,'Deal Pipeline Log'!$T$4:$T$43,0)),"-") -> On track
A25: Stage funnel
A26: Stage | B26: Deals (all) | C26: Active | D26: EBITDA ($M, all) | E26: Prob.-weighted EBITDA ($M)
A27: ='Settings and Scoring Rules'!A19 -> Sourced | B27: =COUNTIF('Deal Pipeline Log'!$G$4:$G$43,$A27) -> 2 | C27: =COUNTIFS('Deal Pipeline Log'!$G$4:$G$43,$A27,'Deal Pipeline Log'!$N$4:$N$43,1) -> 2 | D27: =SUMIF('Deal Pipeline Log'!$G$4:$G$43,$A27,'Deal Pipeline Log'!$H$4:$H$43) -> 7.9 | E27: =SUMIF('Deal Pipeline Log'!$G$4:$G$43,$A27,'Deal Pipeline Log'!$X$4:$X$43) -> 0.395
A28: ='Settings and Scoring Rules'!A20 -> NDA / Teaser | B28: =COUNTIF('Deal Pipeline Log'!$G$4:$G$43,$A28) -> 2 | C28: =COUNTIFS('Deal Pipeline Log'!$G$4:$G$43,$A28,'Deal Pipeline Log'!$N$4:$N$43,1) -> 2 | D28: =SUMIF('Deal Pipeline Log'!$G$4:$G$43,$A28,'Deal Pipeline Log'!$H$4:$H$43) -> 9.1 | E28: =SUMIF('Deal Pipeline Log'!$G$4:$G$43,$A28,'Deal Pipeline Log'!$X$4:$X$43) -> 0.91
A29: ='Settings and Scoring Rules'!A21 -> CIM Review | B29: =COUNTIF('Deal Pipeline Log'!$G$4:$G$43,$A29) -> 2 | C29: =COUNTIFS('Deal Pipeline Log'!$G$4:$G$43,$A29,'Deal Pipeline Log'!$N$4:$N$43,1) -> 2 | D29: =SUMIF('Deal Pipeline Log'!$G$4:$G$43,$A29,'Deal Pipeline Log'!$H$4:$H$43) -> 22.2 | E29: =SUMIF('Deal Pipeline Log'!$G$4:$G$43,$A29,'Deal Pipeline Log'!$X$4:$X$43) -> 4.44
A30: ='Settings and Scoring Rules'!A22 -> IOI Submitted | B30: =COUNTIF('Deal Pipeline Log'!$G$4:$G$43,$A30) -> 2 | C30: =COUNTIFS('Deal Pipeline Log'!$G$4:$G$43,$A30,'Deal Pipeline Log'!$N$4:$N$43,1) -> 2 | D30: =SUMIF('Deal Pipeline Log'!$G$4:$G$43,$A30,'Deal Pipeline Log'!$H$4:$H$43) -> 21.5 | E30: =SUMIF('Deal Pipeline Log'!$G$4:$G$43,$A30,'Deal Pipeline Log'!$X$4:$X$43) -> 7.525
A31: ='Settings and Scoring Rules'!A23 -> Management Meeting | B31: =COUNTIF('Deal Pipeline Log'!$G$4:$G$43,$A31) -> 1 | C31: =COUNTIFS('Deal Pipeline Log'!$G$4:$G$43,$A31,'Deal Pipeline Log'!$N$4:$N$43,1) -> 1 | D31: =SUMIF('Deal Pipeline Log'!$G$4:$G$43,$A31,'Deal Pipeline Log'!$H$4:$H$43) -> 6.5 | E31: =SUMIF('Deal Pipeline Log'!$G$4:$G$43,$A31,'Deal Pipeline Log'!$X$4:$X$43) -> 3.25
A32: ='Settings and Scoring Rules'!A24 -> LOI Submitted | B32: =COUNTIF('Deal Pipeline Log'!$G$4:$G$43,$A32) -> 1 | C32: =COUNTIFS('Deal Pipeline Log'!$G$4:$G$43,$A32,'Deal Pipeline Log'!$N$4:$N$43,1) -> 1 | D32: =SUMIF('Deal Pipeline Log'!$G$4:$G$43,$A32,'Deal Pipeline Log'!$H$4:$H$43) -> 7.8 | E32: =SUMIF('Deal Pipeline Log'!$G$4:$G$43,$A32,'Deal Pipeline Log'!$X$4:$X$43) -> 5.46
A33: ='Settings and Scoring Rules'!A25 -> Exclusivity / Diligence | B33: =COUNTIF('Deal Pipeline Log'!$G$4:$G$43,$A33) -> 0 | C33: =COUNTIFS('Deal Pipeline Log'!$G$4:$G$43,$A33,'Deal Pipeline Log'!$N$4:$N$43,1) -> 0 | D33: =SUMIF('Deal Pipeline Log'!$G$4:$G$43,$A33,'Deal Pipeline Log'!$H$4:$H$43) -> 0 | E33: =SUMIF('Deal Pipeline Log'!$G$4:$G$43,$A33,'Deal Pipeline Log'!$X$4:$X$43) -> 0
A34: ='Settings and Scoring Rules'!A26 -> Closed | B34: =COUNTIF('Deal Pipeline Log'!$G$4:$G$43,$A34) -> 0 | C34: =COUNTIFS('Deal Pipeline Log'!$G$4:$G$43,$A34,'Deal Pipeline Log'!$N$4:$N$43,1) -> 0 | D34: =SUMIF('Deal Pipeline Log'!$G$4:$G$43,$A34,'Deal Pipeline Log'!$H$4:$H$43) -> 0 | E34: =SUMIF('Deal Pipeline Log'!$G$4:$G$43,$A34,'Deal Pipeline Log'!$X$4:$X$43) -> 0
A35: ='Settings and Scoring Rules'!A27 -> Passed | B35: =COUNTIF('Deal Pipeline Log'!$G$4:$G$43,$A35) -> 1 | C35: =COUNTIFS('Deal Pipeline Log'!$G$4:$G$43,$A35,'Deal Pipeline Log'!$N$4:$N$43,1) -> 0 | D35: =SUMIF('Deal Pipeline Log'!$G$4:$G$43,$A35,'Deal Pipeline Log'!$H$4:$H$43) -> 11 | E35: =SUMIF('Deal Pipeline Log'!$G$4:$G$43,$A35,'Deal Pipeline Log'!$X$4:$X$43) -> 0
A36: ='Settings and Scoring Rules'!A28 -> Lost | B36: =COUNTIF('Deal Pipeline Log'!$G$4:$G$43,$A36) -> 1 | C36: =COUNTIFS('Deal Pipeline Log'!$G$4:$G$43,$A36,'Deal Pipeline Log'!$N$4:$N$43,1) -> 0 | D36: =SUMIF('Deal Pipeline Log'!$G$4:$G$43,$A36,'Deal Pipeline Log'!$H$4:$H$43) -> 8 | E36: =SUMIF('Deal Pipeline Log'!$G$4:$G$43,$A36,'Deal Pipeline Log'!$X$4:$X$43) -> 0
A37: Total | B37: =SUM(B27:B36) -> 12 | C37: =SUM(C27:C36) -> 10 | D37: =SUM(D27:D36) -> 94 | E37: =SUM(E27:E36) -> 21.98
A39: Most overdue follow-ups
A40: Item | B40: Name | C40: Days overdue | D40: Action
A41: Most overdue deal action | B41: =IF(MAX('Deal Pipeline Log'!$V$4:$V$43)=0,"None",INDEX('Deal Pipeline Log'!$B$4:$B$43,MATCH(MAX('Deal Pipeline Log'!$V$4:$V$43),'Deal Pipeline Log'!$V$4:$V$43,0))) -> Project Granite | C41: =MAX('Deal Pipeline Log'!$V$4:$V$43) -> 19 | D41: =IF(C41=0,"-",INDEX('Deal Pipeline Log'!$K$4:$K$43,MATCH(C41,'Deal Pipeline Log'!$V$4:$V$43,0))) -> Schedule intro call with owner
A42: Most overdue intermediary touch | B42: =IF(MAX('Follow-Up Cadence Tracker'!$H$5:$H$29)=0,"None",INDEX('Follow-Up Cadence Tracker'!$B$5:$B$29,MATCH(MAX('Follow-Up Cadence Tracker'!$H$5:$H$29),'Follow-Up Cadence Tracker'!$H$5:$H$29,0))) -> Banker I | C42: =MAX('Follow-Up Cadence Tracker'!$H$5:$H$29) -> 66 | D42: =IF(C42=0,"-","Call this week; confirm active mandates") -> Call this week; confirm active mandates
A44: DASHBOARD OUTPUT | B44: ="Top priority: "&B19&" (score "&IFERROR(TEXT(C19,"0.0"),"-")&", "&D19&", via "&E19&"). "&B7&" active of "&B6&" deals; probability-weighted EBITDA $"&TEXT(B10,"0.00")&"M. Follow-ups: "&B11&" overdue deal actions, "&B12&" overdue intermediary touches, "&B13&" due within "&'Settings and Scoring Rules'!$B$7&" days. Most overdue: "&B41&" ("&C41&"d) and "&B42&" ("&C42&"d). Health: "&B15&"." -> Top priority: Project Falcon (score 91.0, LOI Submitted, via Operator H). 10 active of 12 deals; probability-weighted EBITDA $21.98M. Follow-ups: 4 overdue deal actions, 4 overdue intermediary touches, 5 due within 7 days. Most overdue: Project Granite (19d) and Banker I (66d). Health: AT RISK - 8 overdue follow-ups; clear backlog before new outreach.
A45: Pipeline health formula (FORMULATEXT of B15) | B45: =_xlfn.FORMULATEXT(B15) -> =IF(B11+B12=0,"HEALTHY - no overdue follow-ups",IF(B11+B12<=3,"ATTENTION - clear overdue follow-ups this week","AT RISK - "&(B11+B12)&" overdue follow-ups; clear backlog before new outreach"))

Sheet Anonymized Worked Example
A1: Anonymized Worked Example - Sponsor X lower-middle-market pipeline
A2: Code names, regions and scaled figures only. The dataset lives in the Intermediary Directory (rows 4-13) and Deal Pipeline Log (rows 4-15); this tab reads the live outputs.
A3: Scenario
A4: Sponsor X targets $3-15M EBITDA services and distribution businesses. It tracks 10 intermediaries and 12 opportunities. The question for the Monday pipeline meeting is: which deals deserve time this week, and which relationships are slipping?
A6: Live snapshot (links to Ranking Dashboard)
A7: Metric | B7: Value
A8: As-of date | B8: ='Ranking Dashboard'!B4 -> 46299
A9: Deals logged / active | B9: ='Ranking Dashboard'!B6&" / "&'Ranking Dashboard'!B7 -> 12 / 10
A10: Probability-weighted active EBITDA ($M) | B10: ='Ranking Dashboard'!B10 -> 21.98
A11: Overdue deal next actions | B11: ='Ranking Dashboard'!B11 -> 4
A12: Overdue intermediary touches | B12: ='Ranking Dashboard'!B12 -> 4
A13: Pipeline health | B13: ='Ranking Dashboard'!B15 -> AT RISK - 8 overdue follow-ups; clear backlog before new outreach
A14: Rank 1 | B14: ='Ranking Dashboard'!B19&" - score "&TEXT('Ranking Dashboard'!C19,"0.0") -> Project Falcon - score 91.0
A15: Rank 2 | B15: ='Ranking Dashboard'!B20&" - score "&TEXT('Ranking Dashboard'!C20,"0.0") -> Project Atlas - score 79.0
A16: Rank 3 | B16: ='Ranking Dashboard'!B21&" - score "&TEXT('Ranking Dashboard'!C21,"0.0") -> Project Cedar - score 63.5
A18: Named judgment calls
A19: ID | B19: Judgment call | C19: Choice made | D19: Alternative rejected | E19: Live impact | F19: Impact unit | G19: Rationale
A20: JC1 | B20: Project Ember is above the EBITDA band | C20: Keep it with half size credit (0.5) | D20: Exclude it (size fit 0) | E20: =100*'Settings and Scoring Rules'!$B$13*0.5 -> 7.5 | F20: priority points kept | G20: At $18.0M it is within 50% of the $15M ceiling and comes from an A-tier advisor; keep it visible but ranked below in-band deals.
A21: JC2 | B21: Project Birch thesis fit | C21: Fit 3 of 5 | D21: Fit 4 of 5 (size and sector match) | E21: =100*'Settings and Scoring Rules'!$B$12*0.25 -> 7.5 | F21: priority points withheld | G21: Broad auction with an ask above our underwriting view; sector match alone does not earn a 4.
A22: JC3 | B22: Passed and lost deals stay in the log | C22: Keep for intermediary attribution, exclude from ranking | D22: Delete them | E22: =COUNTIF('Deal Pipeline Log'!$N$4:$N$43,0) -> 2 | F22: deals excluded from ranking | G22: Deals-sourced counts show which intermediaries send relevant flow, even when we pass.
A23: JC4 | B23: Fixed as-of date instead of TODAY() | C23: As-of 2026-10-04 | D23: Live TODAY() date | E23: ='Ranking Dashboard'!B11+'Ranking Dashboard'!B12 -> 8 | F23: overdue items frozen | G23: A fixed date keeps the example reproducible for validators; live users switch Settings B4 to =TODAY().
A25: Dashboard output
A26: ='Ranking Dashboard'!B44 -> Top priority: Project Falcon (score 91.0, LOI Submitted, via Operator H). 10 active of 12 deals; probability-weighted EBITDA $21.98M. Follow-ups: 4 overdue deal actions, 4 overdue intermediary touches, 5 due within 7 days. Most overdue: Project Granite (19d) and Banker I (66d). Health: AT RISK - 8 overdue follow-ups; clear backlog before new outreach.
A28: How to read this example
A29: 1. Project Falcon ranks first: proprietary, in-band, at LOI, sourced by a strength-5 operator relationship.
A30: 2. The two most overdue deal actions are early-stage proprietary deals (Granite 19d, Cedar 8d); the most lapsed relationships are Banker I (66d) and CPA F (21d). These are this week's calls.
A31: 3. Change any yellow input (stage, due date, weight) and the rank, flags, dashboard and this tab all recalculate.
